[{"count_fp": "300.00", "created_time": "2026-05-17T09:59:02.96372Z", "no_price_dollars": "0.0010", "taker_book_side": "bid", "taker_outcome_side": "yes", "taker_side": "yes", "ticker": "KXETH15M-26MAY170600-00", "trade_id": "1571364b-5dad-7e6b-0ffb-8fe46bea93f0", "yes_price_dollars": "0.9990"}, {"count_fp": "200.00", "created_time": "2026-05-17T09:58:58.689613Z", "no_price_dollars": "0.0020", "taker_book_side": "bid", "taker_outcome_side": "yes", "taker_side": "yes", "ticker": "KXETH15M-26MAY170600-00", "trade_id": "d7b5dea1-d5b5-6c89-fc05-165bfca02f13", "yes_price_dollars": "0.9980"}, {"count_fp": "1.00", "created_time": "2026-05-17T09:58:58.689613Z", "no_price_dollars": "0.0010", "taker_book_side": "bid", "taker_outcome_side": "yes", "taker_side": "yes", "ticker": "KXETH15M-26MAY170600-00", "trade_id": "a40acad8-c3ca-6ef5-fad1-30389422278e", "yes_price_dollars": "0.9990"}, {"count_fp": "5.00", "created_time": "2026-05-17T09:58:58.689613Z", "no_price_dollars": "0.0050", "taker_book_side": "bid", "taker_outcome_side": "yes", "taker_side": "yes", "ticker": "KXETH15M-26MAY170600-00", "trade_id": "906474af-cc7b-6ab0-ce49-bdc9ecafe66b", "yes_price_dollars": "0.9950"}, {"count_fp": "3.00", "created_time": "2026-05-17T09:58:58.689613Z", "no_price_dollars": "0.0050", "taker_book_side": "bid", "taker_outcome_side": "yes", "taker_side": "yes", "ticker": "KXETH15M-26MAY170600-00", "trade_id": "4dcc3d51-c39b-63e8-d153-1ee640b81ec4", "yes_price_dollars": "0.9950"}, {"count_fp": "100.00", "created_time": "2026-05-17T09:58:58.689613Z", "no_price_dollars": "0.0010", "taker_book_side": "bid", "taker_outcome_side": "yes", "taker_side": "yes", "ticker": "KXETH15M-26MAY170600-00", "trade_id": "4c31a7e0-0322-6af3-f5cd-768b7a245e2b", "yes_price_dollars": "0.9990"}, {"count_fp": "8.00", "created_time": "2026-05-17T09:58:58.689613Z", "no_price_dollars": "0.0050", "taker_book_side": "bid", "taker_outcome_side": "yes", "taker_side": "yes", "ticker": "KXETH15M-26MAY170600-00", "trade_id": "1d8dda7f-73e2-641b-e6f7-91708f54f1be", "yes_price_dollars": "0.9950"}, {"count_fp": "10.00", "created_time": "2026-05-17T09:58:09.221955Z", "no_price_dollars": "0.0050", "taker_book_side": "bid", "taker_outcome_side": "yes", "taker_side": "yes", "ticker": "KXETH15M-26MAY170600-00", "trade_id": "2a049b25-e18a-67d3-3b17-a7c7699d0aaa", "yes_price_dollars": "0.9950"}, {"count_fp": "12.00", "created_time": "2026-05-17T09:57:23.0664Z", "no_price_dollars": "0.0050", "taker_book_side": "bid", "taker_outcome_side": "yes", "taker_side": "yes", "ticker": "KXETH15M-26MAY170600-00", "trade_id": "f4dff195-2fbe-76e3-23fd-ad6bbd84bd6a", "yes_price_dollars": "0.9950"}, {"count_fp": "5.00", "created_time": "2026-05-17T09:57:15.215641Z", "no_price_dollars": "0.0100", "taker_book_side": "ask", "taker_outcome_side": "no", "taker_side": "no", "ticker": "KXETH15M-26MAY170600-00", "trade_id": "af48abc4-d993-7794-d6c5-b1c8b4ab528b", "yes_price_dollars": "0.9900"}, {"count_fp": "20.00", "created_time": "2026-05-17T09:57:15.215641Z", "no_price_dollars": "0.0100", "taker_book_side": "ask", "taker_outcome_side": "no", "taker_side": "no", "ticker": "KXETH15M-26MAY170600-00", "trade_id": "43a5a8c1-3eb3-719b-c15e-236f47b00a6f", "yes_price_dollars": "0.9900"}, {"count_fp": "1.00", "created_time": "2026-05-17T09:56:57.869861Z", "no_price_dollars": "0.0100", "taker_book_side": "ask", "taker_outcome_side": "no", "taker_side": "no", "ticker": "KXETH15M-26MAY170600-00", "trade_id": "1909a9ca-d473-459f-81f6-3f849565477f", "yes_price_dollars": "0.9900"}, {"count_fp": "1.00", "created_time": "2026-05-17T09:56:46.852181Z", "no_price_dollars": "0.0100", "taker_book_side": "ask", "taker_outcome_side": "no", "taker_side": "no", "ticker": "KXETH15M-26MAY170600-00", "trade_id": "197c0f0c-957f-6cb7-50c6-c278b76e26cf", "yes_price_dollars": "0.9900"}, {"count_fp": "1.00", "created_time": "2026-05-17T09:56:35.82022Z", "no_price_dollars": "0.0100", "taker_book_side": "ask", "taker_outcome_side": "no", "taker_side": "no", "ticker": "KXETH15M-26MAY170600-00", "trade_id": "9bb99729-f55b-6b73-9d91-686a9b21e543", "yes_price_dollars": "0.9900"}, {"count_fp": "1.00", "created_time": "2026-05-17T09:56:24.82423Z", "no_price_dollars": "0.0100", "taker_book_side": "ask", "taker_outcome_side": "no", "taker_side": "no", "ticker": "KXETH15M-26MAY170600-00", "trade_id": "196fcebb-0bc7-5273-8779-c32f77d7725f", "yes_price_dollars": "0.9900"}, {"count_fp": "1.00", "created_time": "2026-05-17T09:56:12.795628Z", "no_price_dollars": "0.0100", "taker_book_side": "ask", "taker_outcome_side": "no", "taker_side": "no", "ticker": "KXETH15M-26MAY170600-00", "trade_id": "b5c161bb-4723-7b1f-fec7-75d3f1775817", "yes_price_dollars": "0.9900"}, {"count_fp": "1.00", "created_time": "2026-05-17T09:55:59.259086Z", "no_price_dollars": "0.0100", "taker_book_side": "ask", "taker_outcome_side": "no", "taker_side": "no", "ticker": "KXETH15M-26MAY170600-00", "trade_id": "fa03b703-ca4f-687f-665d-da542c96cb2b", "yes_price_dollars": "0.9900"}, {"count_fp": "2.57", "created_time": "2026-05-17T09:55:22.800494Z", "no_price_dollars": "0.0110", "taker_book_side": "ask", "taker_outcome_side": "no", "taker_side": "no", "ticker": "KXETH15M-26MAY170600-00", "trade_id": "98d5abfd-d57d-59e2-bf94-5272a5447320", "yes_price_dollars": "0.9890"}, {"count_fp": "5.08", "created_time": "2026-05-17T09:55:22.800494Z", "no_price_dollars": "0.0110", "taker_book_side": "ask", "taker_outcome_side": "no", "taker_side": "no", "ticker": "KXETH15M-26MAY170600-00", "trade_id": "1c3c9cf7-c47e-5320-87e3-ddfa057b4ee7", "yes_price_dollars": "0.9890"}, {"count_fp": "0.43", "created_time": "2026-05-17T09:55:06.108214Z", "no_price_dollars": "0.0110", "taker_book_side": "ask", "taker_outcome_side": "no", "taker_side": "no", "ticker": "KXETH15M-26MAY170600-00", "trade_id": "4663143c-885d-7f92-2ca2-d061a0fac33c", "yes_price_dollars": "0.9890"}, {"count_fp": "0.57", "created_time": "2026-05-17T09:55:06.108214Z", "no_price_dollars": "0.0100", "taker_book_side": "ask", "taker_outcome_side": "no", "taker_side": "no", "ticker": "KXETH15M-26MAY170600-00", "trade_id": "22a299fd-2f4b-780a-2a3b-24d42ab39afa", "yes_price_dollars": "0.9900"}, {"count_fp": "59.43", "created_time": "2026-05-17T09:55:05.282128Z", "no_price_dollars": "0.0100", "taker_book_side": "ask", "taker_outcome_side": "no", "taker_side": "no", "ticker": "KXETH15M-26MAY170600-00", "trade_id": "ce169d8f-4593-4ad2-14ff-daa5c1a19f46", "yes_price_dollars": "0.9900"}, {"count_fp": "71.32", "created_time": "2026-05-17T09:55:05.282128Z", "no_price_dollars": "0.0100", "taker_book_side": "ask", "taker_outcome_side": "no", "taker_side": "no", "ticker": "KXETH15M-26MAY170600-00", "trade_id": "43939d87-2ecf-4e18-1b0f-ff8caff361dc", "yes_price_dollars": "0.9900"}, {"count_fp": "79.25", "created_time": "2026-05-17T09:55:05.282128Z", "no_price_dollars": "0.0100", "taker_book_side": "ask", "taker_outcome_side": "no", "taker_side": "no", "ticker": "KXETH15M-26MAY170600-00", "trade_id": "1d37b1f3-1c51-49c1-1b5c-8ef1744ab701", "yes_price_dollars": "0.9900"}, {"count_fp": "0.43", "created_time": "2026-05-17T09:55:02.202206Z", "no_price_dollars": "0.0100", "taker_book_side": "bid", "taker_outcome_side": "yes", "taker_side": "yes", "ticker": "KXETH15M-26MAY170600-00", "trade_id": "3d61b554-2b93-4a4b-b78f-0760dd35d06d", "yes_price_dollars": "0.9900"}, {"count_fp": "7.74", "created_time": "2026-05-17T09:54:54.253794Z", "no_price_dollars": "0.0250", "taker_book_side": "ask", "taker_outcome_side": "no", "taker_side": "no", "ticker": "KXETH15M-26MAY170600-00", "trade_id": "e66d76d4-5ed4-77d6-bdbc-be4960e2e844", "yes_price_dollars": "0.9750"}, {"count_fp": "19.00", "created_time": "2026-05-17T09:54:54.253794Z", "no_price_dollars": "0.0140", "taker_book_side": "ask", "taker_outcome_side": "no", "taker_side": "no", "ticker": "KXETH15M-26MAY170600-00", "trade_id": "734457c2-a949-78c7-83ab-1dbe3e5e3dc7", "yes_price_dollars": "0.9860"}, {"count_fp": "1.00", "created_time": "2026-05-17T09:54:54.253794Z", "no_price_dollars": "0.0140", "taker_book_side": "ask", "taker_outcome_side": "no", "taker_side": "no", "ticker": "KXETH15M-26MAY170600-00", "trade_id": "19e8f406-ecbc-7fa1-b222-afb23ab63697", "yes_price_dollars": "0.9860"}, {"count_fp": "120.00", "created_time": "2026-05-17T09:54:54.253794Z", "no_price_dollars": "0.0200", "taker_book_side": "ask", "taker_outcome_side": "no", "taker_side": "no", "ticker": "KXETH15M-26MAY170600-00", "trade_id": "09eac680-b061-77ae-9118-516dea1540bb", "yes_price_dollars": "0.9800"}, {"count_fp": "90.00", "created_time": "2026-05-17T09:54:54.253794Z", "no_price_dollars": "0.0200", "taker_book_side": "ask", "taker_outcome_side": "no", "taker_side": "no", "ticker": "KXETH15M-26MAY170600-00", "trade_id": "08bd1b74-811e-7e58-a565-38a80ea1b071", "yes_price_dollars": "0.9800"}, {"count_fp": "10.00", "created_time": "2026-05-17T09:54:54.141038Z", "no_price_dollars": "0.0100", "taker_book_side": "bid", "taker_outcome_side": "yes", "taker_side": "yes", "ticker": "KXETH15M-26MAY170600-00", "trade_id": "f8c7a5e5-6393-449c-d330-07e2ac45cfa5", "yes_price_dollars": "0.9900"}, {"count_fp": "20.43", "created_time": "2026-05-17T09:54:54.141038Z", "no_price_dollars": "0.0100", "taker_book_side": "bid", "taker_outcome_side": "yes", "taker_side": "yes", "ticker": "KXETH15M-26MAY170600-00", "trade_id": "f849983a-d656-4047-e20b-55849c0030a9", "yes_price_dollars": "0.9900"}, {"count_fp": "9.57", "created_time": "2026-05-17T09:54:54.141038Z", "no_price_dollars": "0.0100", "taker_book_side": "bid", "taker_outcome_side": "yes", "taker_side": "yes", "ticker": "KXETH15M-26MAY170600-00", "trade_id": "db5b3405-028b-4673-d4fe-61e81244cfdd", "yes_price_dollars": "0.9900"}, {"count_fp": "1.00", "created_time": "2026-05-17T09:54:54.141038Z", "no_price_dollars": "0.0100", "taker_book_side": "bid", "taker_outcome_side": "yes", "taker_side": "yes", "ticker": "KXETH15M-26MAY170600-00", "trade_id": "d0b5ef03-55b5-46cd-e844-ce90be65b859", "yes_price_dollars": "0.9900"}, {"count_fp": "50.00", "created_time": "2026-05-17T09:54:54.141038Z", "no_price_dollars": "0.0100", "taker_book_side": "bid", "taker_outcome_side": "yes", "taker_side": "yes", "ticker": "KXETH15M-26MAY170600-00", "trade_id": "b6b8657b-854e-4891-f136-8f4e87d77bb7", "yes_price_dollars": "0.9900"}, {"count_fp": "1.00", "created_time": "2026-05-17T09:54:54.141038Z", "no_price_dollars": "0.0100", "taker_book_side": "bid", "taker_outcome_side": "yes", "taker_side": "yes", "ticker": "KXETH15M-26MAY170600-00", "trade_id": "ad8eb2ea-2efb-4fbf-fa4e-6f3425f1c258", "yes_price_dollars": "0.9900"}, {"count_fp": "100.00", "created_time": "2026-05-17T09:54:54.141038Z", "no_price_dollars": "0.0100", "taker_book_side": "bid", "taker_outcome_side": "yes", "taker_side": "yes", "ticker": "KXETH15M-26MAY170600-00", "trade_id": "940e1f5f-c9bc-495b-c219-9aebde98b08a", "yes_price_dollars": "0.9900"}, {"count_fp": "1.00", "created_time": "2026-05-17T09:54:54.141038Z", "no_price_dollars": "0.0100", "taker_book_side": "bid", "taker_outcome_side": "yes", "taker_side": "yes", "ticker": "KXETH15M-26MAY170600-00", "trade_id": "7b1481a4-82e9-48a6-f825-850449651734", "yes_price_dollars": "0.9900"}, {"count_fp": "26.00", "created_time": "2026-05-17T09:54:54.141038Z", "no_price_dollars": "0.0100", "taker_book_side": "bid", "taker_outcome_side": "yes", "taker_side": "yes", "ticker": "KXETH15M-26MAY170600-00", "trade_id": "7a52d28d-d401-4ebc-c1d3-d523f4b8d424", "yes_price_dollars": "0.9900"}, {"count_fp": "1.00", "created_time": "2026-05-17T09:54:54.141038Z", "no_price_dollars": "0.0100", "taker_book_side": "bid", "taker_outcome_side": "yes", "taker_side": "yes", "ticker": "KXETH15M-26MAY170600-00", "trade_id": "5f3be580-97ad-4ea0-d10d-7d4b600806c7", "yes_price_dollars": "0.9900"}, {"count_fp": "1.00", "created_time": "2026-05-17T09:54:54.141038Z", "no_price_dollars": "0.0100", "taker_book_side": "bid", "taker_outcome_side": "yes", "taker_side": "yes", "ticker": "KXETH15M-26MAY170600-00", "trade_id": "455c38d0-dec6-4c8e-e1c0-ba72c8ec5ffd", "yes_price_dollars": "0.9900"}, {"count_fp": "29.00", "created_time": "2026-05-17T09:54:54.141038Z", "no_price_dollars": "0.0100", "taker_book_side": "bid", "taker_outcome_side": "yes", "taker_side": "yes", "ticker": "KXETH15M-26MAY170600-00", "trade_id": "2be97fae-4792-4a51-c554-04fe488a20df", "yes_price_dollars": "0.9900"}, {"count_fp": "20.08", "created_time": "2026-05-17T09:54:53.254932Z", "no_price_dollars": "0.0100", "taker_book_side": "bid", "taker_outcome_side": "yes", "taker_side": "yes", "ticker": "KXETH15M-26MAY170600-00", "trade_id": "44449aaf-73a2-68ab-f9a1-77f0e6e78d05", "yes_price_dollars": "0.9900"}, {"count_fp": "1.00", "created_time": "2026-05-17T09:54:52.608742Z", "no_price_dollars": "0.0140", "taker_book_side": "ask", "taker_outcome_side": "no", "taker_side": "no", "ticker": "KXETH15M-26MAY170600-00", "trade_id": "6ff16bb2-5a5d-6e9f-ce53-1e1050d000c7", "yes_price_dollars": "0.9860"}, {"count_fp": "1.00", "created_time": "2026-05-17T09:54:51.194691Z", "no_price_dollars": "0.0110", "taker_book_side": "bid", "taker_outcome_side": "yes", "taker_side": "yes", "ticker": "KXETH15M-26MAY170600-00", "trade_id": "e0c65834-40d5-4f25-cb4a-fc6018c2a090", "yes_price_dollars": "0.9890"}, {"count_fp": "29.68", "created_time": "2026-05-17T09:54:51.194691Z", "no_price_dollars": "0.0120", "taker_book_side": "bid", "taker_outcome_side": "yes", "taker_side": "yes", "ticker": "KXETH15M-26MAY170600-00", "trade_id": "b61782d5-0ddb-47aa-e0b5-55ea69b8a87d", "yes_price_dollars": "0.9880"}, {"count_fp": "26.83", "created_time": "2026-05-17T09:54:51.194691Z", "no_price_dollars": "0.0120", "taker_book_side": "bid", "taker_outcome_side": "yes", "taker_side": "yes", "ticker": "KXETH15M-26MAY170600-00", "trade_id": "b1f7d408-978b-4a3c-fdb5-b73e4364c032", "yes_price_dollars": "0.9880"}, {"count_fp": "50.00", "created_time": "2026-05-17T09:54:51.194691Z", "no_price_dollars": "0.0110", "taker_book_side": "bid", "taker_outcome_side": "yes", "taker_side": "yes", "ticker": "KXETH15M-26MAY170600-00", "trade_id": "74758b81-a072-4b58-d20a-282e6ab9f135", "yes_price_dollars": "0.9890"}, {"count_fp": "10.49", "created_time": "2026-05-17T09:54:51.194691Z", "no_price_dollars": "0.0100", "taker_book_side": "bid", "taker_outcome_side": "yes", "taker_side": "yes", "ticker": "KXETH15M-26MAY170600-00", "trade_id": "54cc4f12-f636-45e3-e431-6b5b56d94acd", "yes_price_dollars": "0.9900"}, {"count_fp": "20.32", "created_time": "2026-05-17T09:54:50.5877Z", "no_price_dollars": "0.0120", "taker_book_side": "bid", "taker_outcome_side": "yes", "taker_side": "yes", "ticker": "KXETH15M-26MAY170600-00", "trade_id": "59400cb1-a19f-598e-a6be-6e4206aa5e51", "yes_price_dollars": "0.9880"}, {"count_fp": "1.00", "created_time": "2026-05-17T09:54:50.07525Z", "no_price_dollars": "0.0150", "taker_book_side": "bid", "taker_outcome_side": "yes", "taker_side": "yes", "ticker": "KXETH15M-26MAY170600-00", "trade_id": "d54253c9-dfa3-78a0-58ee-2fd1589c7dd0", "yes_price_dollars": "0.9850"}, {"count_fp": "20.12", "created_time": "2026-05-17T09:54:50.07525Z", "no_price_dollars": "0.0130", "taker_book_side": "bid", "taker_outcome_side": "yes", "taker_side": "yes", "ticker": "KXETH15M-26MAY170600-00", "trade_id": "57308341-492d-7def-412b-034132a9347c", "yes_price_dollars": "0.9870"}, {"count_fp": "0.58", "created_time": "2026-05-17T09:54:46.470136Z", "no_price_dollars": "0.0200", "taker_book_side": "bid", "taker_outcome_side": "yes", "taker_side": "yes", "ticker": "KXETH15M-26MAY170600-00", "trade_id": "fdbac72c-549e-7762-965f-119279092194", "yes_price_dollars": "0.9800"}, {"count_fp": "12.00", "created_time": "2026-05-17T09:54:46.462197Z", "no_price_dollars": "0.0200", "taker_book_side": "bid", "taker_outcome_side": "yes", "taker_side": "yes", "ticker": "KXETH15M-26MAY170600-00", "trade_id": "e45bdab8-2370-5c04-8f6a-029ab88a7368", "yes_price_dollars": "0.9800"}, {"count_fp": "1.00", "created_time": "2026-05-17T09:54:46.462197Z", "no_price_dollars": "0.0200", "taker_book_side": "bid", "taker_outcome_side": "yes", "taker_side": "yes", "ticker": "KXETH15M-26MAY170600-00", "trade_id": "ba867896-610b-5e36-92b7-2b4608e540a7", "yes_price_dollars": "0.9800"}, {"count_fp": "1.00", "created_time": "2026-05-17T09:54:46.462197Z", "no_price_dollars": "0.0200", "taker_book_side": "bid", "taker_outcome_side": "yes", "taker_side": "yes", "ticker": "KXETH15M-26MAY170600-00", "trade_id": "7d69dda5-ad5a-593a-b155-bc3aaf29c813", "yes_price_dollars": "0.9800"}, {"count_fp": "9.42", "created_time": "2026-05-17T09:54:46.462197Z", "no_price_dollars": "0.0200", "taker_book_side": "bid", "taker_outcome_side": "yes", "taker_side": "yes", "ticker": "KXETH15M-26MAY170600-00", "trade_id": "41b414c0-6706-5876-bd4a-7e74580ca880", "yes_price_dollars": "0.9800"}, {"count_fp": "4.58", "created_time": "2026-05-17T09:54:46.462197Z", "no_price_dollars": "0.0200", "taker_book_side": "bid", "taker_outcome_side": "yes", "taker_side": "yes", "ticker": "KXETH15M-26MAY170600-00", "trade_id": "3630d795-8d55-5fc5-8937-6fd2a39b61e7", "yes_price_dollars": "0.9800"}, {"count_fp": "20.42", "created_time": "2026-05-17T09:54:45.97991Z", "no_price_dollars": "0.0200", "taker_book_side": "bid", "taker_outcome_side": "yes", "taker_side": "yes", "ticker": "KXETH15M-26MAY170600-00", "trade_id": "e2686bd2-31fd-72d9-f7e0-30d165015747", "yes_price_dollars": "0.9800"}, {"count_fp": "20.00", "created_time": "2026-05-17T09:54:45.97991Z", "no_price_dollars": "0.0210", "taker_book_side": "bid", "taker_outcome_side": "yes", "taker_side": "yes", "ticker": "KXETH15M-26MAY170600-00", "trade_id": "d9c42928-b939-7bd0-e23d-6efc48b1dfed", "yes_price_dollars": "0.9790"}, {"count_fp": "23.58", "created_time": "2026-05-17T09:54:45.97991Z", "no_price_dollars": "0.0210", "taker_book_side": "bid", "taker_outcome_side": "yes", "taker_side": "yes", "ticker": "KXETH15M-26MAY170600-00", "trade_id": "a1edfdab-48b8-730c-f577-5b3a80c9cb16", "yes_price_dollars": "0.9790"}, {"count_fp": "15.69", "created_time": "2026-05-17T09:54:45.382759Z", "no_price_dollars": "0.0220", "taker_book_side": "bid", "taker_outcome_side": "yes", "taker_side": "yes", "ticker": "KXETH15M-26MAY170600-00", "trade_id": "ed490ada-ab17-68b8-f796-83618325037d", "yes_price_dollars": "0.9780"}, {"count_fp": "5.80", "created_time": "2026-05-17T09:54:45.382759Z", "no_price_dollars": "0.0220", "taker_book_side": "bid", "taker_outcome_side": "yes", "taker_side": "yes", "ticker": "KXETH15M-26MAY170600-00", "trade_id": "ae640802-de1f-6e31-c44b-d616404cbd83", "yes_price_dollars": "0.9780"}, {"count_fp": "40.25", "created_time": "2026-05-17T09:54:45.353501Z", "no_price_dollars": "0.0220", "taker_book_side": "bid", "taker_outcome_side": "yes", "taker_side": "yes", "ticker": "KXETH15M-26MAY170600-00", "trade_id": "ca3f9376-522b-5284-ee9f-d2ab433e88d1", "yes_price_dollars": "0.9780"}, {"count_fp": "22.56", "created_time": "2026-05-17T09:54:45.349297Z", "no_price_dollars": "0.0220", "taker_book_side": "bid", "taker_outcome_side": "yes", "taker_side": "yes", "ticker": "KXETH15M-26MAY170600-00", "trade_id": "f7379e93-f29f-73e0-6e78-c6212f260b65", "yes_price_dollars": "0.9780"}, {"count_fp": "21.50", "created_time": "2026-05-17T09:54:41.878356Z", "no_price_dollars": "0.0220", "taker_book_side": "bid", "taker_outcome_side": "yes", "taker_side": "yes", "ticker": "KXETH15M-26MAY170600-00", "trade_id": "4dbc1986-65ff-706c-a57f-05ba2f99292d", "yes_price_dollars": "0.9780"}, {"count_fp": "130.92", "created_time": "2026-05-17T09:54:34.976033Z", "no_price_dollars": "0.0300", "taker_book_side": "bid", "taker_outcome_side": "yes", "taker_side": "yes", "ticker": "KXETH15M-26MAY170600-00", "trade_id": "cc5855d9-42a2-4dbc-2b85-4f5c567c7e14", "yes_price_dollars": "0.9700"}, {"count_fp": "95.88", "created_time": "2026-05-17T09:54:22.000422Z", "no_price_dollars": "0.0880", "taker_book_side": "ask", "taker_outcome_side": "no", "taker_side": "no", "ticker": "KXETH15M-26MAY170600-00", "trade_id": "0a8f8171-4672-528b-1533-630df5251d49", "yes_price_dollars": "0.9120"}, {"count_fp": "1.00", "created_time": "2026-05-17T09:54:21.458698Z", "no_price_dollars": "0.0980", "taker_book_side": "ask", "taker_outcome_side": "no", "taker_side": "no", "ticker": "KXETH15M-26MAY170600-00", "trade_id": "f22530a2-0df8-660f-4c83-bf86cf5c9212", "yes_price_dollars": "0.9020"}, {"count_fp": "51.56", "created_time": "2026-05-17T09:54:18.36909Z", "no_price_dollars": "0.0900", "taker_book_side": "ask", "taker_outcome_side": "no", "taker_side": "no", "ticker": "KXETH15M-26MAY170600-00", "trade_id": "052bf696-75c8-4b45-0f97-d928e887fb6d", "yes_price_dollars": "0.9100"}, {"count_fp": "23.44", "created_time": "2026-05-17T09:54:18.368472Z", "no_price_dollars": "0.0900", "taker_book_side": "ask", "taker_outcome_side": "no", "taker_side": "no", "ticker": "KXETH15M-26MAY170600-00", "trade_id": "90ef8e93-c8dc-6e51-f204-f351fad6e241", "yes_price_dollars": "0.9100"}, {"count_fp": "70.39", "created_time": "2026-05-17T09:54:18.238221Z", "no_price_dollars": "0.0580", "taker_book_side": "ask", "taker_outcome_side": "no", "taker_side": "no", "ticker": "KXETH15M-26MAY170600-00", "trade_id": "d8777a2a-0c07-4938-f180-3f7192031917", "yes_price_dollars": "0.9420"}, {"count_fp": "14.84", "created_time": "2026-05-17T09:54:18.238221Z", "no_price_dollars": "0.0580", "taker_book_side": "ask", "taker_outcome_side": "no", "taker_side": "no", "ticker": "KXETH15M-26MAY170600-00", "trade_id": "d504a26d-fdba-4bc3-e73c-71fb075dd6bd", "yes_price_dollars": "0.9420"}, {"count_fp": "29.61", "created_time": "2026-05-17T09:54:18.237016Z", "no_price_dollars": "0.0580", "taker_book_side": "ask", "taker_outcome_side": "no", "taker_side": "no", "ticker": "KXETH15M-26MAY170600-00", "trade_id": "384ddff2-4c63-5d54-ae61-7dad4339b683", "yes_price_dollars": "0.9420"}, {"count_fp": "99.00", "created_time": "2026-05-17T09:54:16.71621Z", "no_price_dollars": "0.0580", "taker_book_side": "ask", "taker_outcome_side": "no", "taker_side": "no", "ticker": "KXETH15M-26MAY170600-00", "trade_id": "b6602c47-daf4-5841-4872-7af0fd9092fe", "yes_price_dollars": "0.9420"}, {"count_fp": "20.00", "created_time": "2026-05-17T09:54:16.71621Z", "no_price_dollars": "0.0740", "taker_book_side": "ask", "taker_outcome_side": "no", "taker_side": "no", "ticker": "KXETH15M-26MAY170600-00", "trade_id": "76cce6d2-646f-5d6d-65f4-50efd98c2737", "yes_price_dollars": "0.9260"}, {"count_fp": "36.28", "created_time": "2026-05-17T09:54:16.71621Z", "no_price_dollars": "0.0800", "taker_book_side": "ask", "taker_outcome_side": "no", "taker_side": "no", "ticker": "KXETH15M-26MAY170600-00", "trade_id": "557d2eb7-50b3-5c05-7cda-c7dc35f451e1", "yes_price_dollars": "0.9200"}, {"count_fp": "20.00", "created_time": "2026-05-17T09:54:16.71621Z", "no_price_dollars": "0.0630", "taker_book_side": "ask", "taker_outcome_side": "no", "taker_side": "no", "ticker": "KXETH15M-26MAY170600-00", "trade_id": "45cdd79d-fc4e-5bae-5c14-d94e223cdb58", "yes_price_dollars": "0.9370"}, {"count_fp": "1.00", "created_time": "2026-05-17T09:54:10.791494Z", "no_price_dollars": "0.0580", "taker_book_side": "ask", "taker_outcome_side": "no", "taker_side": "no", "ticker": "KXETH15M-26MAY170600-00", "trade_id": "cf0aa9fd-eda8-6d99-4f5b-ff753e66e25a", "yes_price_dollars": "0.9420"}, {"count_fp": "320.84", "created_time": "2026-05-17T09:54:06.094932Z", "no_price_dollars": "0.0500", "taker_book_side": "bid", "taker_outcome_side": "yes", "taker_side": "yes", "ticker": "KXETH15M-26MAY170600-00", "trade_id": "fb774c32-06e1-4afc-00f6-06644baef079", "yes_price_dollars": "0.9500"}, {"count_fp": "37.16", "created_time": "2026-05-17T09:54:06.094932Z", "no_price_dollars": "0.0400", "taker_book_side": "bid", "taker_outcome_side": "yes", "taker_side": "yes", "ticker": "KXETH15M-26MAY170600-00", "trade_id": "7887accf-96e5-4f46-31e7-c9513b16a001", "yes_price_dollars": "0.9600"}, {"count_fp": "423.00", "created_time": "2026-05-17T09:54:04.08695Z", "no_price_dollars": "0.0600", "taker_book_side": "bid", "taker_outcome_side": "yes", "taker_side": "yes", "ticker": "KXETH15M-26MAY170600-00", "trade_id": "9d861cf9-26ed-6498-933b-7930be0c00dd", "yes_price_dollars": "0.9400"}, {"count_fp": "26.35", "created_time": "2026-05-17T09:54:04.077297Z", "no_price_dollars": "0.0600", "taker_book_side": "bid", "taker_outcome_side": "yes", "taker_side": "yes", "ticker": "KXETH15M-26MAY170600-00", "trade_id": "55bde5df-55d5-7f3c-e05b-c068eeb45091", "yes_price_dollars": "0.9400"}, {"count_fp": "1.00", "created_time": "2026-05-17T09:54:02.889056Z", "no_price_dollars": "0.0630", "taker_book_side": "bid", "taker_outcome_side": "yes", "taker_side": "yes", "ticker": "KXETH15M-26MAY170600-00", "trade_id": "f4fc53b6-e20e-729b-6035-16b2c94c2069", "yes_price_dollars": "0.9370"}, {"count_fp": "20.00", "created_time": "2026-05-17T09:54:02.154482Z", "no_price_dollars": "0.0620", "taker_book_side": "bid", "taker_outcome_side": "yes", "taker_side": "yes", "ticker": "KXETH15M-26MAY170600-00", "trade_id": "85390d28-cb6b-545d-8040-47f1b86da781", "yes_price_dollars": "0.9380"}, {"count_fp": "5.19", "created_time": "2026-05-17T09:54:02.154482Z", "no_price_dollars": "0.0620", "taker_book_side": "bid", "taker_outcome_side": "yes", "taker_side": "yes", "ticker": "KXETH15M-26MAY170600-00", "trade_id": "5c49fd6b-fc5f-5f8a-a9cf-d5fa906ed38c", "yes_price_dollars": "0.9380"}, {"count_fp": "4.81", "created_time": "2026-05-17T09:54:02.154482Z", "no_price_dollars": "0.0600", "taker_book_side": "bid", "taker_outcome_side": "yes", "taker_side": "yes", "ticker": "KXETH15M-26MAY170600-00", "trade_id": "3fb1690a-cf85-5d00-bedb-8ab2c33c09e1", "yes_price_dollars": "0.9400"}, {"count_fp": "2.00", "created_time": "2026-05-17T09:54:01.837344Z", "no_price_dollars": "0.0880", "taker_book_side": "ask", "taker_outcome_side": "no", "taker_side": "no", "ticker": "KXETH15M-26MAY170600-00", "trade_id": "616a4f2b-7368-7f59-240b-c2523bba4dba", "yes_price_dollars": "0.9120"}, {"count_fp": "49.32", "created_time": "2026-05-17T09:54:01.366441Z", "no_price_dollars": "0.0880", "taker_book_side": "ask", "taker_outcome_side": "no", "taker_side": "no", "ticker": "KXETH15M-26MAY170600-00", "trade_id": "e1dcd297-cc5c-69a9-f62f-fbfe53d2c1d2", "yes_price_dollars": "0.9120"}, {"count_fp": "21.10", "created_time": "2026-05-17T09:54:01.359848Z", "no_price_dollars": "0.0880", "taker_book_side": "ask", "taker_outcome_side": "no", "taker_side": "no", "ticker": "KXETH15M-26MAY170600-00", "trade_id": "0ded31ca-a8dc-7ee5-1671-c8195a588a4e", "yes_price_dollars": "0.9120"}, {"count_fp": "1.00", "created_time": "2026-05-17T09:54:00.170333Z", "no_price_dollars": "0.0520", "taker_book_side": "bid", "taker_outcome_side": "yes", "taker_side": "yes", "ticker": "KXETH15M-26MAY170600-00", "trade_id": "cec0a808-83d7-5606-a61c-fda4ff7feb07", "yes_price_dollars": "0.9480"}, {"count_fp": "74.00", "created_time": "2026-05-17T09:54:00.092036Z", "no_price_dollars": "0.0500", "taker_book_side": "ask", "taker_outcome_side": "no", "taker_side": "no", "ticker": "KXETH15M-26MAY170600-00", "trade_id": "882abcb7-8210-4fe8-f016-a44cd943abba", "yes_price_dollars": "0.9500"}, {"count_fp": "1.00", "created_time": "2026-05-17T09:53:59.52968Z", "no_price_dollars": "0.0500", "taker_book_side": "ask", "taker_outcome_side": "no", "taker_side": "no", "ticker": "KXETH15M-26MAY170600-00", "trade_id": "6b3fab28-cc34-7d7c-159b-bb982cdb61b2", "yes_price_dollars": "0.9500"}, {"count_fp": "500.00", "created_time": "2026-05-17T09:53:51.406184Z", "no_price_dollars": "0.0500", "taker_book_side": "ask", "taker_outcome_side": "no", "taker_side": "no", "ticker": "KXETH15M-26MAY170600-00", "trade_id": "a1f5a0a3-ac2c-6754-85e5-22618413649a", "yes_price_dollars": "0.9500"}, {"count_fp": "90.00", "created_time": "2026-05-17T09:53:51.065741Z", "no_price_dollars": "0.0500", "taker_book_side": "ask", "taker_outcome_side": "no", "taker_side": "no", "ticker": "KXETH15M-26MAY170600-00", "trade_id": "625d7b06-095c-69a5-b8c4-cef43d90d9e1", "yes_price_dollars": "0.9500"}, {"count_fp": "75.00", "created_time": "2026-05-17T09:53:51.018534Z", "no_price_dollars": "0.0400", "taker_book_side": "ask", "taker_outcome_side": "no", "taker_side": "no", "ticker": "KXETH15M-26MAY170600-00", "trade_id": "bdbca31a-9034-730c-79d6-730eee2e885d", "yes_price_dollars": "0.9600"}, {"count_fp": "20.28", "created_time": "2026-05-17T09:53:51.018534Z", "no_price_dollars": "0.0370", "taker_book_side": "ask", "taker_outcome_side": "no", "taker_side": "no", "ticker": "KXETH15M-26MAY170600-00", "trade_id": "785a9bfb-3ed0-73d5-4350-a30a7db8628e", "yes_price_dollars": "0.9630"}, {"count_fp": "5.00", "created_time": "2026-05-17T09:53:51.018534Z", "no_price_dollars": "0.0400", "taker_book_side": "ask", "taker_outcome_side": "no", "taker_side": "no", "ticker": "KXETH15M-26MAY170600-00", "trade_id": "1480ef0c-8c11-7dff-4af8-55da2fc431f6", "yes_price_dollars": "0.9600"}, {"count_fp": "8.35", "created_time": "2026-05-17T09:53:45.656197Z", "no_price_dollars": "0.0370", "taker_book_side": "ask", "taker_outcome_side": "no", "taker_side": "no", "ticker": "KXETH15M-26MAY170600-00", "trade_id": "56eead8a-8961-41d1-115e-490f0212a670", "yes_price_dollars": "0.9630"}, {"count_fp": "18.00", "created_time": "2026-05-17T09:53:45.656197Z", "no_price_dollars": "0.0340", "taker_book_side": "ask", "taker_outcome_side": "no", "taker_side": "no", "ticker": "KXETH15M-26MAY170600-00", "trade_id": "2493bee3-ec1a-4799-100b-69dde0f80400", "yes_price_dollars": "0.9660"}, {"count_fp": "1.00", "created_time": "2026-05-17T09:53:38.930066Z", "no_price_dollars": "0.0210", "taker_book_side": "bid", "taker_outcome_side": "yes", "taker_side": "yes", "ticker": "KXETH15M-26MAY170600-00", "trade_id": "21f7ad65-b550-4c38-d482-22513a71e93a", "yes_price_dollars": "0.9790"}, {"count_fp": "1.00", "created_time": "2026-05-17T09:53:34.121269Z", "no_price_dollars": "0.0340", "taker_book_side": "ask", "taker_outcome_side": "no", "taker_side": "no", "ticker": "KXETH15M-26MAY170600-00", "trade_id": "0607dcff-608e-6479-8d81-690846c70e08", "yes_price_dollars": "0.9660"}, {"count_fp": "1.00", "created_time": "2026-05-17T09:53:29.728951Z", "no_price_dollars": "0.0210", "taker_book_side": "bid", "taker_outcome_side": "yes", "taker_side": "yes", "ticker": "KXETH15M-26MAY170600-00", "trade_id": "d46ce511-51b8-4130-bbf7-1379650a1b1a", "yes_price_dollars": "0.9790"}, {"count_fp": "14.63", "created_time": "2026-05-17T09:53:28.247542Z", "no_price_dollars": "0.0220", "taker_book_side": "bid", "taker_outcome_side": "yes", "taker_side": "yes", "ticker": "KXETH15M-26MAY170600-00", "trade_id": "e9a1601b-06f9-7777-c9e9-39f53341e8c3", "yes_price_dollars": "0.9780"}, {"count_fp": "76.00", "created_time": "2026-05-17T09:53:28.247542Z", "no_price_dollars": "0.0220", "taker_book_side": "bid", "taker_outcome_side": "yes", "taker_side": "yes", "ticker": "KXETH15M-26MAY170600-00", "trade_id": "3301ca3f-a3fc-797c-e91b-bb5c34796d2c", "yes_price_dollars": "0.9780"}, {"count_fp": "164.42", "created_time": "2026-05-17T09:53:28.247542Z", "no_price_dollars": "0.0210", "taker_book_side": "bid", "taker_outcome_side": "yes", "taker_side": "yes", "ticker": "KXETH15M-26MAY170600-00", "trade_id": "15b0cf47-006c-74f0-c7aa-28ff72da67f6", "yes_price_dollars": "0.9790"}, {"count_fp": "7.00", "created_time": "2026-05-17T09:53:25.748425Z", "no_price_dollars": "0.0220", "taker_book_side": "bid", "taker_outcome_side": "yes", "taker_side": "yes", "ticker": "KXETH15M-26MAY170600-00", "trade_id": "16ff1303-2628-49d4-87f4-99cc6c89db28", "yes_price_dollars": "0.9780"}, {"count_fp": "1.00", "created_time": "2026-05-17T09:53:23.707203Z", "no_price_dollars": "0.0220", "taker_book_side": "bid", "taker_outcome_side": "yes", "taker_side": "yes", "ticker": "KXETH15M-26MAY170600-00", "trade_id": "aa85aa35-971a-4a77-9d80-3e44d39f2ed5", "yes_price_dollars": "0.9780"}, {"count_fp": "1.00", "created_time": "2026-05-17T09:53:23.707203Z", "no_price_dollars": "0.0250", "taker_book_side": "bid", "taker_outcome_side": "yes", "taker_side": "yes", "ticker": "KXETH15M-26MAY170600-00", "trade_id": "805c152f-b932-4680-b1f5-a92598fc6ca0", "yes_price_dollars": "0.9750"}, {"count_fp": "14.00", "created_time": "2026-05-17T09:53:23.707203Z", "no_price_dollars": "0.0230", "taker_book_side": "bid", "taker_outcome_side": "yes", "taker_side": "yes", "ticker": "KXETH15M-26MAY170600-00", "trade_id": "2f795eb9-dc60-4085-8544-8d0c7fe1b8c6", "yes_price_dollars": "0.9770"}, {"count_fp": "17.00", "created_time": "2026-05-17T09:53:23.707203Z", "no_price_dollars": "0.0220", "taker_book_side": "bid", "taker_outcome_side": "yes", "taker_side": "yes", "ticker": "KXETH15M-26MAY170600-00", "trade_id": "1b52f0be-3af4-4ac4-b204-e29146e1b7ac", "yes_price_dollars": "0.9780"}, {"count_fp": "1.00", "created_time": "2026-05-17T09:53:22.107046Z", "no_price_dollars": "0.0340", "taker_book_side": "ask", "taker_outcome_side": "no", "taker_side": "no", "ticker": "KXETH15M-26MAY170600-00", "trade_id": "3c992704-0302-53b9-0307-7016dd5a8818", "yes_price_dollars": "0.9660"}, {"count_fp": "33.00", "created_time": "2026-05-17T09:53:13.009502Z", "no_price_dollars": "0.0300", "taker_book_side": "bid", "taker_outcome_side": "yes", "taker_side": "yes", "ticker": "KXETH15M-26MAY170600-00", "trade_id": "1e0702c9-a494-57ba-5cef-60af6ceb23bc", "yes_price_dollars": "0.9700"}, {"count_fp": "1.00", "created_time": "2026-05-17T09:53:11.370189Z", "no_price_dollars": "0.0300", "taker_book_side": "bid", "taker_outcome_side": "yes", "taker_side": "yes", "ticker": "KXETH15M-26MAY170600-00", "trade_id": "ceadf12c-34dc-6eda-43d2-671ea44bb38c", "yes_price_dollars": "0.9700"}, {"count_fp": "1.00", "created_time": "2026-05-17T09:53:09.624057Z", "no_price_dollars": "0.0300", "taker_book_side": "bid", "taker_outcome_side": "yes", "taker_side": "yes", "ticker": "KXETH15M-26MAY170600-00", "trade_id": "fdc0701b-2954-6ff6-d608-c79d105ef6d0", "yes_price_dollars": "0.9700"}, {"count_fp": "1.00", "created_time": "2026-05-17T09:53:09.624057Z", "no_price_dollars": "0.0300", "taker_book_side": "bid", "taker_outcome_side": "yes", "taker_side": "yes", "ticker": "KXETH15M-26MAY170600-00", "trade_id": "e0e5233d-98ca-6651-e5dd-9623656003af", "yes_price_dollars": "0.9700"}, {"count_fp": "23.00", "created_time": "2026-05-17T09:53:09.624057Z", "no_price_dollars": "0.0300", "taker_book_side": "bid", "taker_outcome_side": "yes", "taker_side": "yes", "ticker": "KXETH15M-26MAY170600-00", "trade_id": "8bdcbd08-18be-6d83-ce76-d921c7ebb8f4", "yes_price_dollars": "0.9700"}, {"count_fp": "8.00", "created_time": "2026-05-17T09:53:09.624057Z", "no_price_dollars": "0.0300", "taker_book_side": "bid", "taker_outcome_side": "yes", "taker_side": "yes", "ticker": "KXETH15M-26MAY170600-00", "trade_id": "14c3ad93-e154-6e22-fe0a-557641c6dd44", "yes_price_dollars": "0.9700"}, {"count_fp": "1.00", "created_time": "2026-05-17T09:53:08.604932Z", "no_price_dollars": "0.0440", "taker_book_side": "ask", "taker_outcome_side": "no", "taker_side": "no", "ticker": "KXETH15M-26MAY170600-00", "trade_id": "85121849-6f07-58a7-127a-14be9a9da0ec", "yes_price_dollars": "0.9560"}, {"count_fp": "1.00", "created_time": "2026-05-17T09:53:04.121873Z", "no_price_dollars": "0.0310", "taker_book_side": "bid", "taker_outcome_side": "yes", "taker_side": "yes", "ticker": "KXETH15M-26MAY170600-00", "trade_id": "a1f766f2-274d-6aa8-75ea-3ca76795725c", "yes_price_dollars": "0.9690"}, {"count_fp": "1.00", "created_time": "2026-05-17T09:53:04.121873Z", "no_price_dollars": "0.0330", "taker_book_side": "bid", "taker_outcome_side": "yes", "taker_side": "yes", "ticker": "KXETH15M-26MAY170600-00", "trade_id": "50e1638c-df21-6290-68a9-997b75500e72", "yes_price_dollars": "0.9670"}, {"count_fp": "8.00", "created_time": "2026-05-17T09:53:04.121873Z", "no_price_dollars": "0.0310", "taker_book_side": "bid", "taker_outcome_side": "yes", "taker_side": "yes", "ticker": "KXETH15M-26MAY170600-00", "trade_id": "2e65d438-aa46-6c4f-42ec-4f907be9e444", "yes_price_dollars": "0.9690"}, {"count_fp": "20.49", "created_time": "2026-05-17T09:52:50.403906Z", "no_price_dollars": "0.0470", "taker_book_side": "ask", "taker_outcome_side": "no", "taker_side": "no", "ticker": "KXETH15M-26MAY170600-00", "trade_id": "74276ea0-01ed-4444-1966-fbfae46d90e8", "yes_price_dollars": "0.9530"}, {"count_fp": "75.00", "created_time": "2026-05-17T09:52:50.403906Z", "no_price_dollars": "0.0500", "taker_book_side": "ask", "taker_outcome_side": "no", "taker_side": "no", "ticker": "KXETH15M-26MAY170600-00", "trade_id": "24d09677-87e1-483f-0c88-922b180146e3", "yes_price_dollars": "0.9500"}, {"count_fp": "25.47", "created_time": "2026-05-17T09:52:39.559273Z", "no_price_dollars": "0.0480", "taker_book_side": "ask", "taker_outcome_side": "no", "taker_side": "no", "ticker": "KXETH15M-26MAY170600-00", "trade_id": "e1c08876-c800-755d-c7bf-22a0d6f5011a", "yes_price_dollars": "0.9520"}, {"count_fp": "20.43", "created_time": "2026-05-17T09:52:39.559273Z", "no_price_dollars": "0.0440", "taker_book_side": "ask", "taker_outcome_side": "no", "taker_side": "no", "ticker": "KXETH15M-26MAY170600-00", "trade_id": "afb2782d-6108-7cca-e3de-2efc63b8e356", "yes_price_dollars": "0.9560"}, {"count_fp": "20.00", "created_time": "2026-05-17T09:52:39.559273Z", "no_price_dollars": "0.0440", "taker_book_side": "ask", "taker_outcome_side": "no", "taker_side": "no", "ticker": "KXETH15M-26MAY170600-00", "trade_id": "6a3e4dd7-05a4-74b7-f3f6-3b3ad25d6f67", "yes_price_dollars": "0.9560"}, {"count_fp": "2.00", "created_time": "2026-05-17T09:52:30.491772Z", "no_price_dollars": "0.0400", "taker_book_side": "bid", "taker_outcome_side": "yes", "taker_side": "yes", "ticker": "KXETH15M-26MAY170600-00", "trade_id": "f9de05e1-820c-4da1-753a-ff54541fc6a0", "yes_price_dollars": "0.9600"}, {"count_fp": "22.00", "created_time": "2026-05-17T09:52:26.363989Z", "no_price_dollars": "0.0400", "taker_book_side": "bid", "taker_outcome_side": "yes", "taker_side": "yes", "ticker": "KXETH15M-26MAY170600-00", "trade_id": "27d6a18c-d0e4-6ba5-8f45-3b9b9ad61a54", "yes_price_dollars": "0.9600"}, {"count_fp": "19.00", "created_time": "2026-05-17T09:52:26.343171Z", "no_price_dollars": "0.0400", "taker_book_side": "bid", "taker_outcome_side": "yes", "taker_side": "yes", "ticker": "KXETH15M-26MAY170600-00", "trade_id": "75f63d18-225c-75b1-7fa6-dda105a3a894", "yes_price_dollars": "0.9600"}, {"count_fp": "17.00", "created_time": "2026-05-17T09:52:26.322858Z", "no_price_dollars": "0.0400", "taker_book_side": "bid", "taker_outcome_side": "yes", "taker_side": "yes", "ticker": "KXETH15M-26MAY170600-00", "trade_id": "27eb5a66-e954-7895-dafa-1de2129f4458", "yes_price_dollars": "0.9600"}, {"count_fp": "1.00", "created_time": "2026-05-17T09:52:26.302187Z", "no_price_dollars": "0.0400", "taker_book_side": "bid", "taker_outcome_side": "yes", "taker_side": "yes", "ticker": "KXETH15M-26MAY170600-00", "trade_id": "d909b034-d026-5452-73f0-0de78cce5d52", "yes_price_dollars": "0.9600"}, {"count_fp": "3.00", "created_time": "2026-05-17T09:52:26.302187Z", "no_price_dollars": "0.0400", "taker_book_side": "bid", "taker_outcome_side": "yes", "taker_side": "yes", "ticker": "KXETH15M-26MAY170600-00", "trade_id": "c9fc9389-f3f4-57bd-4993-c16389f7a260", "yes_price_dollars": "0.9600"}, {"count_fp": "1.00", "created_time": "2026-05-17T09:52:26.302187Z", "no_price_dollars": "0.0440", "taker_book_side": "bid", "taker_outcome_side": "yes", "taker_side": "yes", "ticker": "KXETH15M-26MAY170600-00", "trade_id": "51417cda-08e9-5b8c-78eb-0c762779452b", "yes_price_dollars": "0.9560"}, {"count_fp": "90.00", "created_time": "2026-05-17T09:52:24.734508Z", "no_price_dollars": "0.0600", "taker_book_side": "ask", "taker_outcome_side": "no", "taker_side": "no", "ticker": "KXETH15M-26MAY170600-00", "trade_id": "992ae468-6929-5413-ba30-84a8dd17aee5", "yes_price_dollars": "0.9400"}, {"count_fp": "20.00", "created_time": "2026-05-17T09:52:24.734508Z", "no_price_dollars": "0.0610", "taker_book_side": "ask", "taker_outcome_side": "no", "taker_side": "no", "ticker": "KXETH15M-26MAY170600-00", "trade_id": "5f7bb50c-0506-5928-addb-94a206c16aa0", "yes_price_dollars": "0.9390"}, {"count_fp": "73.00", "created_time": "2026-05-17T09:52:24.734508Z", "no_price_dollars": "0.0700", "taker_book_side": "ask", "taker_outcome_side": "no", "taker_side": "no", "ticker": "KXETH15M-26MAY170600-00", "trade_id": "594956bf-6fb4-54a1-a75f-201e9d9cf1f7", "yes_price_dollars": "0.9300"}, {"count_fp": "100.00", "created_time": "2026-05-17T09:52:24.734508Z", "no_price_dollars": "0.0480", "taker_book_side": "ask", "taker_outcome_side": "no", "taker_side": "no", "ticker": "KXETH15M-26MAY170600-00", "trade_id": "44be4a56-b9a9-5cf4-9d3e-f94b705402ed", "yes_price_dollars": "0.9520"}, {"count_fp": "20.00", "created_time": "2026-05-17T09:52:24.734508Z", "no_price_dollars": "0.0510", "taker_book_side": "ask", "taker_outcome_side": "no", "taker_side": "no", "ticker": "KXETH15M-26MAY170600-00", "trade_id": "11a6dd55-8c32-5fb4-949e-7330be328b26", "yes_price_dollars": "0.9490"}, {"count_fp": "13.23", "created_time": "2026-05-17T09:52:21.068916Z", "no_price_dollars": "0.0500", "taker_book_side": "bid", "taker_outcome_side": "yes", "taker_side": "yes", "ticker": "KXETH15M-26MAY170600-00", "trade_id": "8fa8f7eb-2aa2-6838-f275-9d650f25c918", "yes_price_dollars": "0.9500"}, {"count_fp": "20.00", "created_time": "2026-05-17T09:52:21.068916Z", "no_price_dollars": "0.0500", "taker_book_side": "bid", "taker_outcome_side": "yes", "taker_side": "yes", "ticker": "KXETH15M-26MAY170600-00", "trade_id": "34c7c8f1-448a-6c8b-fff9-998a0c8a7639", "yes_price_dollars": "0.9500"}, {"count_fp": "1.00", "created_time": "2026-05-17T09:52:21.034071Z", "no_price_dollars": "0.0500", "taker_book_side": "bid", "taker_outcome_side": "yes", "taker_side": "yes", "ticker": "KXETH15M-26MAY170600-00", "trade_id": "d0aa14f2-b5be-4898-7137-e84e5d28c6e3", "yes_price_dollars": "0.9500"}, {"count_fp": "5.77", "created_time": "2026-05-17T09:52:21.034071Z", "no_price_dollars": "0.0500", "taker_book_side": "bid", "taker_outcome_side": "yes", "taker_side": "yes", "ticker": "KXETH15M-26MAY170600-00", "trade_id": "bf4b5326-4fb2-41c8-4037-707dae9082a0", "yes_price_dollars": "0.9500"}, {"count_fp": "6.31", "created_time": "2026-05-17T09:52:21.034071Z", "no_price_dollars": "0.0510", "taker_book_side": "bid", "taker_outcome_side": "yes", "taker_side": "yes", "ticker": "KXETH15M-26MAY170600-00", "trade_id": "b4a49a21-3422-47c9-4e2a-4fca7ad2b592", "yes_price_dollars": "0.9490"}, {"count_fp": "6.00", "created_time": "2026-05-17T09:52:21.034071Z", "no_price_dollars": "0.0500", "taker_book_side": "bid", "taker_outcome_side": "yes", "taker_side": "yes", "ticker": "KXETH15M-26MAY170600-00", "trade_id": "771d8d63-39b0-419e-6c0b-4ed601125270", "yes_price_dollars": "0.9500"}, {"count_fp": "1.00", "created_time": "2026-05-17T09:52:21.034071Z", "no_price_dollars": "0.0550", "taker_book_side": "bid", "taker_outcome_side": "yes", "taker_side": "yes", "ticker": "KXETH15M-26MAY170600-00", "trade_id": "0f14a454-6237-4fac-7f6a-ca8a7a7816aa", "yes_price_dollars": "0.9450"}, {"count_fp": "10.91", "created_time": "2026-05-17T09:52:20.107264Z", "no_price_dollars": "0.0700", "taker_book_side": "bid", "taker_outcome_side": "yes", "taker_side": "yes", "ticker": "KXETH15M-26MAY170600-00", "trade_id": "e22e9441-a226-4e5e-0d27-5ae72819257b", "yes_price_dollars": "0.9300"}, {"count_fp": "1.00", "created_time": "2026-05-17T09:52:20.107264Z", "no_price_dollars": "0.0660", "taker_book_side": "bid", "taker_outcome_side": "yes", "taker_side": "yes", "ticker": "KXETH15M-26MAY170600-00", "trade_id": "dd718a9f-ca86-4e74-2dd4-5163d182aa39", "yes_price_dollars": "0.9340"}, {"count_fp": "25.00", "created_time": "2026-05-17T09:52:20.107264Z", "no_price_dollars": "0.0600", "taker_book_side": "bid", "taker_outcome_side": "yes", "taker_side": "yes", "ticker": "KXETH15M-26MAY170600-00", "trade_id": "bf369f59-f5fe-4822-08cc-47a439763244", "yes_price_dollars": "0.9400"}, {"count_fp": "12.00", "created_time": "2026-05-17T09:52:20.107264Z", "no_price_dollars": "0.0600", "taker_book_side": "bid", "taker_outcome_side": "yes", "taker_side": "yes", "ticker": "KXETH15M-26MAY170600-00", "trade_id": "a89dc8cb-3aff-4e00-1aaf-5fc5e2259daa", "yes_price_dollars": "0.9400"}, {"count_fp": "235.09", "created_time": "2026-05-17T09:52:20.107264Z", "no_price_dollars": "0.0600", "taker_book_side": "bid", "taker_outcome_side": "yes", "taker_side": "yes", "ticker": "KXETH15M-26MAY170600-00", "trade_id": "724edf92-cc44-4541-2d43-b7a60406e718", "yes_price_dollars": "0.9400"}, {"count_fp": "1.00", "created_time": "2026-05-17T09:52:20.107264Z", "no_price_dollars": "0.0600", "taker_book_side": "bid", "taker_outcome_side": "yes", "taker_side": "yes", "ticker": "KXETH15M-26MAY170600-00", "trade_id": "3f4030da-14bd-4602-016c-c18402552d54", "yes_price_dollars": "0.9400"}, {"count_fp": "1.00", "created_time": "2026-05-17T09:52:20.107264Z", "no_price_dollars": "0.0700", "taker_book_side": "bid", "taker_outcome_side": "yes", "taker_side": "yes", "ticker": "KXETH15M-26MAY170600-00", "trade_id": "2f832d41-305b-4e54-2d20-1d06da6eb154", "yes_price_dollars": "0.9300"}, {"count_fp": "1.00", "created_time": "2026-05-17T09:52:13.237531Z", "no_price_dollars": "0.0700", "taker_book_side": "bid", "taker_outcome_side": "yes", "taker_side": "yes", "ticker": "KXETH15M-26MAY170600-00", "trade_id": "ebc66527-d9f9-5f34-29f2-1cba19f55613", "yes_price_dollars": "0.9300"}, {"count_fp": "1.09", "created_time": "2026-05-17T09:52:13.237531Z", "no_price_dollars": "0.0700", "taker_book_side": "bid", "taker_outcome_side": "yes", "taker_side": "yes", "ticker": "KXETH15M-26MAY170600-00", "trade_id": "3e4aec2f-20ba-584e-2032-9b339d51a4ef", "yes_price_dollars": "0.9300"}, {"count_fp": "1.00", "created_time": "2026-05-17T09:52:10.356571Z", "no_price_dollars": "0.0980", "taker_book_side": "ask", "taker_outcome_side": "no", "taker_side": "no", "ticker": "KXETH15M-26MAY170600-00", "trade_id": "21df0776-62c6-5fe0-cfcd-be0a8d18ade7", "yes_price_dollars": "0.9020"}, {"count_fp": "13.00", "created_time": "2026-05-17T09:52:10.103929Z", "no_price_dollars": "0.0700", "taker_book_side": "bid", "taker_outcome_side": "yes", "taker_side": "yes", "ticker": "KXETH15M-26MAY170600-00", "trade_id": "913bd0a2-a7d3-76e0-2106-c774d732774c", "yes_price_dollars": "0.9300"}, {"count_fp": "4.00", "created_time": "2026-05-17T09:52:10.103929Z", "no_price_dollars": "0.0700", "taker_book_side": "bid", "taker_outcome_side": "yes", "taker_side": "yes", "ticker": "KXETH15M-26MAY170600-00", "trade_id": "4c3b35d9-39f3-798b-0568-987906b44dcf", "yes_price_dollars": "0.9300"}, {"count_fp": "15.00", "created_time": "2026-05-17T09:52:08.675954Z", "no_price_dollars": "0.0900", "taker_book_side": "ask", "taker_outcome_side": "no", "taker_side": "no", "ticker": "KXETH15M-26MAY170600-00", "trade_id": "8675607f-fd3c-5c9b-6101-259ce60445ca", "yes_price_dollars": "0.9100"}, {"count_fp": "1.00", "created_time": "2026-05-17T09:52:04.676724Z", "no_price_dollars": "0.0800", "taker_book_side": "bid", "taker_outcome_side": "yes", "taker_side": "yes", "ticker": "KXETH15M-26MAY170600-00", "trade_id": "cc4e2085-ffae-6b55-efe9-caec8e2c19f1", "yes_price_dollars": "0.9200"}, {"count_fp": "15.00", "created_time": "2026-05-17T09:52:01.316211Z", "no_price_dollars": "0.0800", "taker_book_side": "bid", "taker_outcome_side": "yes", "taker_side": "yes", "ticker": "KXETH15M-26MAY170600-00", "trade_id": "93f3ab3f-4eca-5a69-6e23-658cb0906311", "yes_price_dollars": "0.9200"}, {"count_fp": "1.00", "created_time": "2026-05-17T09:51:58.18029Z", "no_price_dollars": "0.0800", "taker_book_side": "bid", "taker_outcome_side": "yes", "taker_side": "yes", "ticker": "KXETH15M-26MAY170600-00", "trade_id": "dbbb118b-3c57-402a-7943-11868f513e84", "yes_price_dollars": "0.9200"}, {"count_fp": "1.00", "created_time": "2026-05-17T09:51:58.18029Z", "no_price_dollars": "0.0800", "taker_book_side": "bid", "taker_outcome_side": "yes", "taker_side": "yes", "ticker": "KXETH15M-26MAY170600-00", "trade_id": "91756173-207c-4f7e-7ec9-439d5ce1e438", "yes_price_dollars": "0.9200"}, {"count_fp": "13.00", "created_time": "2026-05-17T09:51:58.18029Z", "no_price_dollars": "0.0800", "taker_book_side": "bid", "taker_outcome_side": "yes", "taker_side": "yes", "ticker": "KXETH15M-26MAY170600-00", "trade_id": "82a63a62-37fe-46bd-5082-cd4361d9d7cd", "yes_price_dollars": "0.9200"}, {"count_fp": "3.00", "created_time": "2026-05-17T09:51:48.093223Z", "no_price_dollars": "0.1100", "taker_book_side": "ask", "taker_outcome_side": "no", "taker_side": "no", "ticker": "KXETH15M-26MAY170600-00", "trade_id": "6f6b9d31-5d14-652b-700f-71599801bf74", "yes_price_dollars": "0.8900"}, {"count_fp": "2.00", "created_time": "2026-05-17T09:51:48.058531Z", "no_price_dollars": "0.1000", "taker_book_side": "ask", "taker_outcome_side": "no", "taker_side": "no", "ticker": "KXETH15M-26MAY170600-00", "trade_id": "4a7de135-ec8c-698b-e788-e0c7e8136890", "yes_price_dollars": "0.9000"}, {"count_fp": "14.00", "created_time": "2026-05-17T09:51:45.349911Z", "no_price_dollars": "0.0900", "taker_book_side": "ask", "taker_outcome_side": "no", "taker_side": "no", "ticker": "KXETH15M-26MAY170600-00", "trade_id": "acf5a479-4def-7056-2742-614e13a42b79", "yes_price_dollars": "0.9100"}, {"count_fp": "2.00", "created_time": "2026-05-17T09:51:45.349911Z", "no_price_dollars": "0.0900", "taker_book_side": "ask", "taker_outcome_side": "no", "taker_side": "no", "ticker": "KXETH15M-26MAY170600-00", "trade_id": "a1afadaf-58fa-7e67-31b4-25e446a6442b", "yes_price_dollars": "0.9100"}, {"count_fp": "1.00", "created_time": "2026-05-17T09:51:44.050729Z", "no_price_dollars": "0.0880", "taker_book_side": "bid", "taker_outcome_side": "yes", "taker_side": "yes", "ticker": "KXETH15M-26MAY170600-00", "trade_id": "6c8f42ea-9af5-756e-cdf1-cc0deb45beb7", "yes_price_dollars": "0.9120"}, {"count_fp": "13.00", "created_time": "2026-05-17T09:51:44.050729Z", "no_price_dollars": "0.0850", "taker_book_side": "bid", "taker_outcome_side": "yes", "taker_side": "yes", "ticker": "KXETH15M-26MAY170600-00", "trade_id": "048786de-3f81-7525-c607-d2e13a3a385b", "yes_price_dollars": "0.9150"}, {"count_fp": "1.00", "created_time": "2026-05-17T09:51:42.328747Z", "no_price_dollars": "0.0900", "taker_book_side": "bid", "taker_outcome_side": "yes", "taker_side": "yes", "ticker": "KXETH15M-26MAY170600-00", "trade_id": "29c80599-c85a-7e3b-296c-2d8b51b3eaab", "yes_price_dollars": "0.9100"}, {"count_fp": "3.00", "created_time": "2026-05-17T09:51:40.379917Z", "no_price_dollars": "0.1000", "taker_book_side": "bid", "taker_outcome_side": "yes", "taker_side": "yes", "ticker": "KXETH15M-26MAY170600-00", "trade_id": "d65bc43e-634d-6dfb-9418-3ce2c49938f5", "yes_price_dollars": "0.9000"}, {"count_fp": "9.00", "created_time": "2026-05-17T09:51:40.379917Z", "no_price_dollars": "0.1000", "taker_book_side": "bid", "taker_outcome_side": "yes", "taker_side": "yes", "ticker": "KXETH15M-26MAY170600-00", "trade_id": "50f3db32-d75c-6082-8023-343bbc4b4b8b", "yes_price_dollars": "0.9000"}, {"count_fp": "1.00", "created_time": "2026-05-17T09:51:40.379917Z", "no_price_dollars": "0.1000", "taker_book_side": "bid", "taker_outcome_side": "yes", "taker_side": "yes", "ticker": "KXETH15M-26MAY170600-00", "trade_id": "2fab63df-12ae-6585-a4ee-2a146d1350fd", "yes_price_dollars": "0.9000"}, {"count_fp": "1.00", "created_time": "2026-05-17T09:51:30.376838Z", "no_price_dollars": "0.1400", "taker_book_side": "ask", "taker_outcome_side": "no", "taker_side": "no", "ticker": "KXETH15M-26MAY170600-00", "trade_id": "c496668b-2e13-7d3e-64e9-5c4f28ccae3a", "yes_price_dollars": "0.8600"}, {"count_fp": "11.00", "created_time": "2026-05-17T09:51:30.376838Z", "no_price_dollars": "0.1500", "taker_book_side": "ask", "taker_outcome_side": "no", "taker_side": "no", "ticker": "KXETH15M-26MAY170600-00", "trade_id": "8f89dc37-ed2a-7d24-507e-3aa4b65c3412", "yes_price_dollars": "0.8500"}, {"count_fp": "20.00", "created_time": "2026-05-17T09:51:30.376838Z", "no_price_dollars": "0.1400", "taker_book_side": "ask", "taker_outcome_side": "no", "taker_side": "no", "ticker": "KXETH15M-26MAY170600-00", "trade_id": "852d08c7-2069-7512-79e8-da1d2b2ad505", "yes_price_dollars": "0.8600"}, {"count_fp": "100.00", "created_time": "2026-05-17T09:51:30.376838Z", "no_price_dollars": "0.1400", "taker_book_side": "ask", "taker_outcome_side": "no", "taker_side": "no", "ticker": "KXETH15M-26MAY170600-00", "trade_id": "1854c56e-2703-7ff4-74b5-d3fd2f0ce936", "yes_price_dollars": "0.8600"}, {"count_fp": "6.00", "created_time": "2026-05-17T09:51:12.367761Z", "no_price_dollars": "0.1200", "taker_book_side": "bid", "taker_outcome_side": "yes", "taker_side": "yes", "ticker": "KXETH15M-26MAY170600-00", "trade_id": "7ead9cff-91cc-4178-54cb-a8fcca6a76b4", "yes_price_dollars": "0.8800"}, {"count_fp": "1.78", "created_time": "2026-05-17T09:51:03.773379Z", "no_price_dollars": "0.1100", "taker_book_side": "bid", "taker_outcome_side": "yes", "taker_side": "yes", "ticker": "KXETH15M-26MAY170600-00", "trade_id": "f1bcd15c-e69e-55f0-02da-7263be552959", "yes_price_dollars": "0.8900"}, {"count_fp": "20.00", "created_time": "2026-05-17T09:51:03.773379Z", "no_price_dollars": "0.1200", "taker_book_side": "bid", "taker_outcome_side": "yes", "taker_side": "yes", "ticker": "KXETH15M-26MAY170600-00", "trade_id": "a2c301e8-492d-5921-3437-82acc4a9aa36", "yes_price_dollars": "0.8800"}, {"count_fp": "7.22", "created_time": "2026-05-17T09:51:03.773379Z", "no_price_dollars": "0.1100", "taker_book_side": "bid", "taker_outcome_side": "yes", "taker_side": "yes", "ticker": "KXETH15M-26MAY170600-00", "trade_id": "917fdcd9-a10d-5a55-27e9-4936c7d39fc2", "yes_price_dollars": "0.8900"}, {"count_fp": "1.00", "created_time": "2026-05-17T09:51:03.773379Z", "no_price_dollars": "0.1100", "taker_book_side": "bid", "taker_outcome_side": "yes", "taker_side": "yes", "ticker": "KXETH15M-26MAY170600-00", "trade_id": "624fe32b-0bd3-51de-09db-f7c8d0daeec4", "yes_price_dollars": "0.8900"}, {"count_fp": "6.00", "created_time": "2026-05-17T09:51:00.733701Z", "no_price_dollars": "0.1100", "taker_book_side": "bid", "taker_outcome_side": "yes", "taker_side": "yes", "ticker": "KXETH15M-26MAY170600-00", "trade_id": "8be50f41-d9e2-4adf-8eb7-77dfb08de02a", "yes_price_dollars": "0.8900"}, {"count_fp": "1.00", "created_time": "2026-05-17T09:51:00.733701Z", "no_price_dollars": "0.1300", "taker_book_side": "bid", "taker_outcome_side": "yes", "taker_side": "yes", "ticker": "KXETH15M-26MAY170600-00", "trade_id": "79bd3171-404d-4e14-9dce-5af0364623be", "yes_price_dollars": "0.8700"}, {"count_fp": "17.22", "created_time": "2026-05-17T09:51:00.733701Z", "no_price_dollars": "0.1100", "taker_book_side": "bid", "taker_outcome_side": "yes", "taker_side": "yes", "ticker": "KXETH15M-26MAY170600-00", "trade_id": "70b984d6-50de-48a4-b11a-cdcc629d4369", "yes_price_dollars": "0.8900"}, {"count_fp": "1.00", "created_time": "2026-05-17T09:51:00.731488Z", "no_price_dollars": "0.1300", "taker_book_side": "bid", "taker_outcome_side": "yes", "taker_side": "yes", "ticker": "KXETH15M-26MAY170600-00", "trade_id": "5aef6e62-bf14-7e65-742a-615af13b1188", "yes_price_dollars": "0.8700"}, {"count_fp": "6.00", "created_time": "2026-05-17T09:51:00.731488Z", "no_price_dollars": "0.1300", "taker_book_side": "bid", "taker_outcome_side": "yes", "taker_side": "yes", "ticker": "KXETH15M-26MAY170600-00", "trade_id": "4f7ec725-ebdd-79a9-5d61-501c16c777e4", "yes_price_dollars": "0.8700"}, {"count_fp": "4.00", "created_time": "2026-05-17T09:51:00.731488Z", "no_price_dollars": "0.1300", "taker_book_side": "bid", "taker_outcome_side": "yes", "taker_side": "yes", "ticker": "KXETH15M-26MAY170600-00", "trade_id": "34d35505-f735-78cc-6b4a-fa07a9552e76", "yes_price_dollars": "0.8700"}, {"count_fp": "9.00", "created_time": "2026-05-17T09:50:54.855727Z", "no_price_dollars": "0.1500", "taker_book_side": "bid", "taker_outcome_side": "yes", "taker_side": "yes", "ticker": "KXETH15M-26MAY170600-00", "trade_id": "dda43da8-3f5f-6294-a2be-47f51d9edcec", "yes_price_dollars": "0.8500"}, {"count_fp": "14.00", "created_time": "2026-05-17T09:50:46.511971Z", "no_price_dollars": "0.1800", "taker_book_side": "ask", "taker_outcome_side": "no", "taker_side": "no", "ticker": "KXETH15M-26MAY170600-00", "trade_id": "ee41e6e1-1f3e-446f-4588-e06ec6a11127", "yes_price_dollars": "0.8200"}, {"count_fp": "78.00", "created_time": "2026-05-17T09:50:45.954887Z", "no_price_dollars": "0.1800", "taker_book_side": "ask", "taker_outcome_side": "no", "taker_side": "no", "ticker": "KXETH15M-26MAY170600-00", "trade_id": "6574a291-a32e-5f1b-d487-d8440ec8f51f", "yes_price_dollars": "0.8200"}, {"count_fp": "18.00", "created_time": "2026-05-17T09:50:40.167754Z", "no_price_dollars": "0.1800", "taker_book_side": "ask", "taker_outcome_side": "no", "taker_side": "no", "ticker": "KXETH15M-26MAY170600-00", "trade_id": "698e307e-b56e-65b3-6a5a-129a3a40c353", "yes_price_dollars": "0.8200"}, {"count_fp": "1.00", "created_time": "2026-05-17T09:50:38.389091Z", "no_price_dollars": "0.1700", "taker_book_side": "bid", "taker_outcome_side": "yes", "taker_side": "yes", "ticker": "KXETH15M-26MAY170600-00", "trade_id": "c8a4928b-ea44-5bb7-17be-bb9430ccc42c", "yes_price_dollars": "0.8300"}, {"count_fp": "4.00", "created_time": "2026-05-17T09:50:38.389091Z", "no_price_dollars": "0.1700", "taker_book_side": "bid", "taker_outcome_side": "yes", "taker_side": "yes", "ticker": "KXETH15M-26MAY170600-00", "trade_id": "bb60d742-cdca-5ae6-1c3a-fb7a17c64d6c", "yes_price_dollars": "0.8300"}, {"count_fp": "7.00", "created_time": "2026-05-17T09:50:33.406338Z", "no_price_dollars": "0.2000", "taker_book_side": "bid", "taker_outcome_side": "yes", "taker_side": "yes", "ticker": "KXETH15M-26MAY170600-00", "trade_id": "dafb339d-b233-7b15-3563-f9f4f8f9e962", "yes_price_dollars": "0.8000"}, {"count_fp": "7.00", "created_time": "2026-05-17T09:50:30.830667Z", "no_price_dollars": "0.2000", "taker_book_side": "bid", "taker_outcome_side": "yes", "taker_side": "yes", "ticker": "KXETH15M-26MAY170600-00", "trade_id": "0ba3da7e-7205-41dd-26f1-77eb75f230c8", "yes_price_dollars": "0.8000"}, {"count_fp": "1.00", "created_time": "2026-05-17T09:50:26.019229Z", "no_price_dollars": "0.1900", "taker_book_side": "bid", "taker_outcome_side": "yes", "taker_side": "yes", "ticker": "KXETH15M-26MAY170600-00", "trade_id": "ecaad2b8-2fa7-7879-e003-8cc1b24f5cd3", "yes_price_dollars": "0.8100"}, {"count_fp": "5.00", "created_time": "2026-05-17T09:50:08.109516Z", "no_price_dollars": "0.2400", "taker_book_side": "bid", "taker_outcome_side": "yes", "taker_side": "yes", "ticker": "KXETH15M-26MAY170600-00", "trade_id": "23e6ef47-6ce7-5553-a5a1-51ef1e0249f6", "yes_price_dollars": "0.7600"}, {"count_fp": "1.50", "created_time": "2026-05-17T09:50:07.510813Z", "no_price_dollars": "0.2500", "taker_book_side": "ask", "taker_outcome_side": "no", "taker_side": "no", "ticker": "KXETH15M-26MAY170600-00", "trade_id": "8dac99e6-7c27-4698-d5f0-19e85440fd66", "yes_price_dollars": "0.7500"}, {"count_fp": "1.00", "created_time": "2026-05-17T09:50:07.510813Z", "no_price_dollars": "0.2500", "taker_book_side": "ask", "taker_outcome_side": "no", "taker_side": "no", "ticker": "KXETH15M-26MAY170600-00", "trade_id": "721cf214-92a0-4e85-e8e0-0ad7fb9f715b", "yes_price_dollars": "0.7500"}, {"count_fp": "2.17", "created_time": "2026-05-17T09:50:05.303467Z", "no_price_dollars": "0.2300", "taker_book_side": "bid", "taker_outcome_side": "yes", "taker_side": "yes", "ticker": "KXETH15M-26MAY170600-00", "trade_id": "fcd139f0-17ff-6492-68c8-5d74c8e26646", "yes_price_dollars": "0.7700"}, {"count_fp": "5.00", "created_time": "2026-05-17T09:50:04.682972Z", "no_price_dollars": "0.2500", "taker_book_side": "ask", "taker_outcome_side": "no", "taker_side": "no", "ticker": "KXETH15M-26MAY170600-00", "trade_id": "d112439d-8cc2-772b-7c4e-ba4e47d4cdb3", "yes_price_dollars": "0.7500"}, {"count_fp": "14.00", "created_time": "2026-05-17T09:49:59.2451Z", "no_price_dollars": "0.2500", "taker_book_side": "ask", "taker_outcome_side": "no", "taker_side": "no", "ticker": "KXETH15M-26MAY170600-00", "trade_id": "32a15e5c-79de-715b-4493-2a074f96fc4b", "yes_price_dollars": "0.7500"}, {"count_fp": "70.00", "created_time": "2026-05-17T09:49:58.489319Z", "no_price_dollars": "0.2500", "taker_book_side": "ask", "taker_outcome_side": "no", "taker_side": "no", "ticker": "KXETH15M-26MAY170600-00", "trade_id": "c04a67a2-bf02-45af-5a99-196ceae7a88f", "yes_price_dollars": "0.7500"}, {"count_fp": "20.00", "created_time": "2026-05-17T09:49:55.77373Z", "no_price_dollars": "0.2500", "taker_book_side": "bid", "taker_outcome_side": "yes", "taker_side": "yes", "ticker": "KXETH15M-26MAY170600-00", "trade_id": "673d2f92-80bb-6fc7-3e54-16d10721ed48", "yes_price_dollars": "0.7500"}, {"count_fp": "5.00", "created_time": "2026-05-17T09:49:55.421954Z", "no_price_dollars": "0.2500", "taker_book_side": "bid", "taker_outcome_side": "yes", "taker_side": "yes", "ticker": "KXETH15M-26MAY170600-00", "trade_id": "e3650b57-be26-43f4-e9f2-eaf87f5ab644", "yes_price_dollars": "0.7500"}, {"count_fp": "20.00", "created_time": "2026-05-17T09:49:55.205729Z", "no_price_dollars": "0.2600", "taker_book_side": "bid", "taker_outcome_side": "yes", "taker_side": "yes", "ticker": "KXETH15M-26MAY170600-00", "trade_id": "80ccca95-d8a8-64eb-f371-d626f76a60e6", "yes_price_dollars": "0.7400"}, {"count_fp": "20.00", "created_time": "2026-05-17T09:49:53.577412Z", "no_price_dollars": "0.2600", "taker_book_side": "bid", "taker_outcome_side": "yes", "taker_side": "yes", "ticker": "KXETH15M-26MAY170600-00", "trade_id": "5acd2d8c-65ab-642f-a325-a3cd60571a3e", "yes_price_dollars": "0.7400"}, {"count_fp": "20.00", "created_time": "2026-05-17T09:49:52.899455Z", "no_price_dollars": "0.2600", "taker_book_side": "bid", "taker_outcome_side": "yes", "taker_side": "yes", "ticker": "KXETH15M-26MAY170600-00", "trade_id": "3be91791-a9f6-5b9f-cb89-24e3e73ea9b1", "yes_price_dollars": "0.7400"}, {"count_fp": "10.00", "created_time": "2026-05-17T09:49:52.450762Z", "no_price_dollars": "0.2800", "taker_book_side": "bid", "taker_outcome_side": "yes", "taker_side": "yes", "ticker": "KXETH15M-26MAY170600-00", "trade_id": "eb95c789-bff1-477b-9ee7-2c4ef7f602af", "yes_price_dollars": "0.7200"}, {"count_fp": "1.00", "created_time": "2026-05-17T09:49:52.450762Z", "no_price_dollars": "0.2800", "taker_book_side": "bid", "taker_outcome_side": "yes", "taker_side": "yes", "ticker": "KXETH15M-26MAY170600-00", "trade_id": "03daa21a-695c-4d24-9872-a118f4d5c368", "yes_price_dollars": "0.7200"}, {"count_fp": "10.00", "created_time": "2026-05-17T09:49:50.107778Z", "no_price_dollars": "0.2900", "taker_book_side": "bid", "taker_outcome_side": "yes", "taker_side": "yes", "ticker": "KXETH15M-26MAY170600-00", "trade_id": "eb74da57-fd35-6d12-f94c-34c04392df6c", "yes_price_dollars": "0.7100"}, {"count_fp": "20.00", "created_time": "2026-05-17T09:49:50.107778Z", "no_price_dollars": "0.3000", "taker_book_side": "bid", "taker_outcome_side": "yes", "taker_side": "yes", "ticker": "KXETH15M-26MAY170600-00", "trade_id": "8fc3f20c-72a2-6dc4-da39-1c655bab0a79", "yes_price_dollars": "0.7000"}, {"count_fp": "6.00", "created_time": "2026-05-17T09:49:45.222293Z", "no_price_dollars": "0.3100", "taker_book_side": "bid", "taker_outcome_side": "yes", "taker_side": "yes", "ticker": "KXETH15M-26MAY170600-00", "trade_id": "9be64efb-a4f5-4b32-35fe-2b3cec85487a", "yes_price_dollars": "0.6900"}, {"count_fp": "5.00", "created_time": "2026-05-17T09:49:44.66997Z", "no_price_dollars": "0.3100", "taker_book_side": "bid", "taker_outcome_side": "yes", "taker_side": "yes", "ticker": "KXETH15M-26MAY170600-00", "trade_id": "5954a061-5fd9-691e-013b-e56187c57282", "yes_price_dollars": "0.6900"}, {"count_fp": "6.00", "created_time": "2026-05-17T09:49:37.811994Z", "no_price_dollars": "0.3100", "taker_book_side": "bid", "taker_outcome_side": "yes", "taker_side": "yes", "ticker": "KXETH15M-26MAY170600-00", "trade_id": "e4435aa0-9195-41e2-7d82-09990dbc7996", "yes_price_dollars": "0.6900"}, {"count_fp": "27.73", "created_time": "2026-05-17T09:49:31.450882Z", "no_price_dollars": "0.3300", "taker_book_side": "ask", "taker_outcome_side": "no", "taker_side": "no", "ticker": "KXETH15M-26MAY170600-00", "trade_id": "2de9a2f9-792e-425e-91c2-0aafd76ba436", "yes_price_dollars": "0.6700"}, {"count_fp": "20.00", "created_time": "2026-05-17T09:49:31.419645Z", "no_price_dollars": "0.3200", "taker_book_side": "bid", "taker_outcome_side": "yes", "taker_side": "yes", "ticker": "KXETH15M-26MAY170600-00", "trade_id": "6c489e7d-73f8-4c03-4f9d-094ac831dfd4", "yes_price_dollars": "0.6800"}, {"count_fp": "10.00", "created_time": "2026-05-17T09:49:28.50816Z", "no_price_dollars": "0.3500", "taker_book_side": "bid", "taker_outcome_side": "yes", "taker_side": "yes", "ticker": "KXETH15M-26MAY170600-00", "trade_id": "d3dd60db-6d4f-4ba4-7057-0f7a64d0cd1a", "yes_price_dollars": "0.6500"}, {"count_fp": "20.00", "created_time": "2026-05-17T09:49:28.50816Z", "no_price_dollars": "0.3600", "taker_book_side": "bid", "taker_outcome_side": "yes", "taker_side": "yes", "ticker": "KXETH15M-26MAY170600-00", "trade_id": "03f92c1f-d5cd-4474-6023-bdd3ea2d2f76", "yes_price_dollars": "0.6400"}, {"count_fp": "20.00", "created_time": "2026-05-17T09:49:25.728411Z", "no_price_dollars": "0.3600", "taker_book_side": "bid", "taker_outcome_side": "yes", "taker_side": "yes", "ticker": "KXETH15M-26MAY170600-00", "trade_id": "42795948-d0cf-4bbd-1dd2-609f50c89913", "yes_price_dollars": "0.6400"}, {"count_fp": "5.11", "created_time": "2026-05-17T09:49:25.728411Z", "no_price_dollars": "0.3500", "taker_book_side": "bid", "taker_outcome_side": "yes", "taker_side": "yes", "ticker": "KXETH15M-26MAY170600-00", "trade_id": "1348ff6b-2047-4030-2ff0-7917b907b886", "yes_price_dollars": "0.6500"}, {"count_fp": "0.72", "created_time": "2026-05-17T09:49:24.248675Z", "no_price_dollars": "0.3800", "taker_book_side": "bid", "taker_outcome_side": "yes", "taker_side": "yes", "ticker": "KXETH15M-26MAY170600-00", "trade_id": "904eb237-13eb-7b2f-6a37-b51a16b6d208", "yes_price_dollars": "0.6200"}, {"count_fp": "11.11", "created_time": "2026-05-17T09:49:24.231352Z", "no_price_dollars": "0.3800", "taker_book_side": "bid", "taker_outcome_side": "yes", "taker_side": "yes", "ticker": "KXETH15M-26MAY170600-00", "trade_id": "a0afa43c-35ab-58b3-44e9-c21cf4229e50", "yes_price_dollars": "0.6200"}, {"count_fp": "94.89", "created_time": "2026-05-17T09:49:24.231352Z", "no_price_dollars": "0.3800", "taker_book_side": "bid", "taker_outcome_side": "yes", "taker_side": "yes", "ticker": "KXETH15M-26MAY170600-00", "trade_id": "46dd3f64-3039-5b8e-6494-c9333315e4e8", "yes_price_dollars": "0.6200"}, {"count_fp": "20.00", "created_time": "2026-05-17T09:49:24.231352Z", "no_price_dollars": "0.3800", "taker_book_side": "bid", "taker_outcome_side": "yes", "taker_side": "yes", "ticker": "KXETH15M-26MAY170600-00", "trade_id": "29b0bbbd-f953-5588-7ed0-b9bd5909a960", "yes_price_dollars": "0.6200"}, {"count_fp": "12.29", "created_time": "2026-05-17T09:49:17.447281Z", "no_price_dollars": "0.3900", "taker_book_side": "ask", "taker_outcome_side": "no", "taker_side": "no", "ticker": "KXETH15M-26MAY170600-00", "trade_id": "a954f483-11d4-4feb-8481-ab323080accd", "yes_price_dollars": "0.6100"}, {"count_fp": "20.00", "created_time": "2026-05-17T09:49:06.375059Z", "no_price_dollars": "0.3800", "taker_book_side": "bid", "taker_outcome_side": "yes", "taker_side": "yes", "ticker": "KXETH15M-26MAY170600-00", "trade_id": "f2660e17-c4f6-4054-9978-9d470df9cda0", "yes_price_dollars": "0.6200"}, {"count_fp": "5.11", "created_time": "2026-05-17T09:49:06.375059Z", "no_price_dollars": "0.3800", "taker_book_side": "bid", "taker_outcome_side": "yes", "taker_side": "yes", "ticker": "KXETH15M-26MAY170600-00", "trade_id": "a142cb39-cee5-4512-b5cb-c01f3f0cc3b0", "yes_price_dollars": "0.6200"}, {"count_fp": "1.00", "created_time": "2026-05-17T09:49:01.045223Z", "no_price_dollars": "0.3500", "taker_book_side": "bid", "taker_outcome_side": "yes", "taker_side": "yes", "ticker": "KXETH15M-26MAY170600-00", "trade_id": "45da24a3-3c93-58e4-4f39-092f14d113ce", "yes_price_dollars": "0.6500"}, {"count_fp": "3.00", "created_time": "2026-05-17T09:48:59.361548Z", "no_price_dollars": "0.3500", "taker_book_side": "bid", "taker_outcome_side": "yes", "taker_side": "yes", "ticker": "KXETH15M-26MAY170600-00", "trade_id": "add7c438-498b-70b0-784a-67590e93b4de", "yes_price_dollars": "0.6500"}, {"count_fp": "15.24", "created_time": "2026-05-17T09:48:54.774436Z", "no_price_dollars": "0.3600", "taker_book_side": "ask", "taker_outcome_side": "no", "taker_side": "no", "ticker": "KXETH15M-26MAY170600-00", "trade_id": "d88b570d-7c9a-649c-e07c-9334a45f25d2", "yes_price_dollars": "0.6400"}, {"count_fp": "17.00", "created_time": "2026-05-17T09:48:54.485679Z", "no_price_dollars": "0.3500", "taker_book_side": "bid", "taker_outcome_side": "yes", "taker_side": "yes", "ticker": "KXETH15M-26MAY170600-00", "trade_id": "eed44a1e-efe5-55b3-14c8-429742f1eae1", "yes_price_dollars": "0.6500"}, {"count_fp": "5.00", "created_time": "2026-05-17T09:48:54.485679Z", "no_price_dollars": "0.3500", "taker_book_side": "bid", "taker_outcome_side": "yes", "taker_side": "yes", "ticker": "KXETH15M-26MAY170600-00", "trade_id": "aa30c50a-5b46-5696-1492-cd8526fcea3c", "yes_price_dollars": "0.6500"}, {"count_fp": "26.32", "created_time": "2026-05-17T09:48:51.754566Z", "no_price_dollars": "0.3600", "taker_book_side": "ask", "taker_outcome_side": "no", "taker_side": "no", "ticker": "KXETH15M-26MAY170600-00", "trade_id": "9d1c0fa5-cfca-7fac-0cab-5f320fc604b2", "yes_price_dollars": "0.6400"}, {"count_fp": "3.00", "created_time": "2026-05-17T09:48:50.748884Z", "no_price_dollars": "0.3500", "taker_book_side": "bid", "taker_outcome_side": "yes", "taker_side": "yes", "ticker": "KXETH15M-26MAY170600-00", "trade_id": "be55160a-0bbd-5cff-0d6b-9fe85a37300d", "yes_price_dollars": "0.6500"}, {"count_fp": "75.00", "created_time": "2026-05-17T09:48:48.709768Z", "no_price_dollars": "0.3500", "taker_book_side": "bid", "taker_outcome_side": "yes", "taker_side": "yes", "ticker": "KXETH15M-26MAY170600-00", "trade_id": "b80f6bea-f8c2-6cd5-25de-83097dfb8da0", "yes_price_dollars": "0.6500"}, {"count_fp": "10.00", "created_time": "2026-05-17T09:48:48.709768Z", "no_price_dollars": "0.3500", "taker_book_side": "bid", "taker_outcome_side": "yes", "taker_side": "yes", "ticker": "KXETH15M-26MAY170600-00", "trade_id": "880d29fa-c614-6f8e-1e6d-4e31e5c8dee8", "yes_price_dollars": "0.6500"}, {"count_fp": "40.00", "created_time": "2026-05-17T09:48:48.627938Z", "no_price_dollars": "0.3500", "taker_book_side": "bid", "taker_outcome_side": "yes", "taker_side": "yes", "ticker": "KXETH15M-26MAY170600-00", "trade_id": "1a6ddb81-6ddd-4daf-22f4-bd070f154880", "yes_price_dollars": "0.6500"}, {"count_fp": "7.00", "created_time": "2026-05-17T09:48:37.005041Z", "no_price_dollars": "0.4200", "taker_book_side": "ask", "taker_outcome_side": "no", "taker_side": "no", "ticker": "KXETH15M-26MAY170600-00", "trade_id": "1421b2ba-302a-79a0-1c35-1c4d1b5cc4b1", "yes_price_dollars": "0.5800"}, {"count_fp": "7.00", "created_time": "2026-05-17T09:48:26.096764Z", "no_price_dollars": "0.4500", "taker_book_side": "bid", "taker_outcome_side": "yes", "taker_side": "yes", "ticker": "KXETH15M-26MAY170600-00", "trade_id": "cdf01d10-2675-6a58-7fe6-66955e1a14eb", "yes_price_dollars": "0.5500"}, {"count_fp": "1.00", "created_time": "2026-05-17T09:48:25.901097Z", "no_price_dollars": "0.4300", "taker_book_side": "ask", "taker_outcome_side": "no", "taker_side": "no", "ticker": "KXETH15M-26MAY170600-00", "trade_id": "e6e19c52-6e0c-4b78-aa59-26d983fb3f14", "yes_price_dollars": "0.5700"}, {"count_fp": "15.00", "created_time": "2026-05-17T09:48:25.901097Z", "no_price_dollars": "0.4300", "taker_book_side": "ask", "taker_outcome_side": "no", "taker_side": "no", "ticker": "KXETH15M-26MAY170600-00", "trade_id": "d790ab4a-c363-4f7f-91dd-dee275d8ef69", "yes_price_dollars": "0.5700"}, {"count_fp": "20.00", "created_time": "2026-05-17T09:48:18.783644Z", "no_price_dollars": "0.3900", "taker_book_side": "bid", "taker_outcome_side": "yes", "taker_side": "yes", "ticker": "KXETH15M-26MAY170600-00", "trade_id": "7d48d7d5-18da-5d99-8b51-9a218014e74f", "yes_price_dollars": "0.6100"}, {"count_fp": "2.08", "created_time": "2026-05-17T09:47:55.244703Z", "no_price_dollars": "0.4100", "taker_book_side": "bid", "taker_outcome_side": "yes", "taker_side": "yes", "ticker": "KXETH15M-26MAY170600-00", "trade_id": "0dfbb71a-7cc8-70f8-d598-596943bbd788", "yes_price_dollars": "0.5900"}, {"count_fp": "8.18", "created_time": "2026-05-17T09:47:49.338339Z", "no_price_dollars": "0.4300", "taker_book_side": "bid", "taker_outcome_side": "yes", "taker_side": "yes", "ticker": "KXETH15M-26MAY170600-00", "trade_id": "36fe2e7b-6b62-642d-9dd8-58702b511f64", "yes_price_dollars": "0.5700"}, {"count_fp": "20.00", "created_time": "2026-05-17T09:47:40.070952Z", "no_price_dollars": "0.3700", "taker_book_side": "bid", "taker_outcome_side": "yes", "taker_side": "yes", "ticker": "KXETH15M-26MAY170600-00", "trade_id": "f9ccc908-c665-5761-4497-fddd59f89661", "yes_price_dollars": "0.6300"}, {"count_fp": "12.55", "created_time": "2026-05-17T09:47:39.298322Z", "no_price_dollars": "0.3900", "taker_book_side": "bid", "taker_outcome_side": "yes", "taker_side": "yes", "ticker": "KXETH15M-26MAY170600-00", "trade_id": "2e001d70-8bc4-6142-aecc-86fee5870fbe", "yes_price_dollars": "0.6100"}, {"count_fp": "15.00", "created_time": "2026-05-17T09:47:39.298322Z", "no_price_dollars": "0.3900", "taker_book_side": "bid", "taker_outcome_side": "yes", "taker_side": "yes", "ticker": "KXETH15M-26MAY170600-00", "trade_id": "04bfcc98-e44e-6fa5-9158-48b363901ce2", "yes_price_dollars": "0.6100"}, {"count_fp": "2.00", "created_time": "2026-05-17T09:47:39.285443Z", "no_price_dollars": "0.4000", "taker_book_side": "bid", "taker_outcome_side": "yes", "taker_side": "yes", "ticker": "KXETH15M-26MAY170600-00", "trade_id": "e0bc711d-37c1-7d42-452a-27bf48383787", "yes_price_dollars": "0.6000"}, {"count_fp": "100.00", "created_time": "2026-05-17T09:47:39.282505Z", "no_price_dollars": "0.4100", "taker_book_side": "bid", "taker_outcome_side": "yes", "taker_side": "yes", "ticker": "KXETH15M-26MAY170600-00", "trade_id": "9dbc8f93-7fd4-4e10-70f5-09719cec554d", "yes_price_dollars": "0.5900"}, {"count_fp": "3.00", "created_time": "2026-05-17T09:47:34.1107Z", "no_price_dollars": "0.4200", "taker_book_side": "bid", "taker_outcome_side": "yes", "taker_side": "yes", "ticker": "KXETH15M-26MAY170600-00", "trade_id": "4ca2a000-ff0a-4e0e-bbd5-2e22f7d4b64f", "yes_price_dollars": "0.5800"}, {"count_fp": "8.16", "created_time": "2026-05-17T09:47:26.383183Z", "no_price_dollars": "0.4200", "taker_book_side": "bid", "taker_outcome_side": "yes", "taker_side": "yes", "ticker": "KXETH15M-26MAY170600-00", "trade_id": "23df2378-4fb2-60ba-1b03-cf80562c25cf", "yes_price_dollars": "0.5800"}, {"count_fp": "26.91", "created_time": "2026-05-17T09:46:49.949092Z", "no_price_dollars": "0.4600", "taker_book_side": "bid", "taker_outcome_side": "yes", "taker_side": "yes", "ticker": "KXETH15M-26MAY170600-00", "trade_id": "4f0180d1-db84-72b8-4957-35f3a3acb57d", "yes_price_dollars": "0.5400"}, {"count_fp": "8.81", "created_time": "2026-05-17T09:46:37.334323Z", "no_price_dollars": "0.4500", "taker_book_side": "bid", "taker_outcome_side": "yes", "taker_side": "yes", "ticker": "KXETH15M-26MAY170600-00", "trade_id": "22939a61-2ebb-7071-fb37-c57b0a941d0e", "yes_price_dollars": "0.5500"}, {"count_fp": "5.28", "created_time": "2026-05-17T09:46:36.247517Z", "no_price_dollars": "0.4600", "taker_book_side": "bid", "taker_outcome_side": "yes", "taker_side": "yes", "ticker": "KXETH15M-26MAY170600-00", "trade_id": "fe79d971-d83c-4528-d351-fe7555e48b19", "yes_price_dollars": "0.5400"}, {"count_fp": "2.00", "created_time": "2026-05-17T09:46:13.250723Z", "no_price_dollars": "0.4500", "taker_book_side": "bid", "taker_outcome_side": "yes", "taker_side": "yes", "ticker": "KXETH15M-26MAY170600-00", "trade_id": "7dffbdeb-e0d4-483c-83f8-9760c19f2995", "yes_price_dollars": "0.5500"}, {"count_fp": "16.14", "created_time": "2026-05-17T09:46:01.394824Z", "no_price_dollars": "0.4600", "taker_book_side": "bid", "taker_outcome_side": "yes", "taker_side": "yes", "ticker": "KXETH15M-26MAY170600-00", "trade_id": "22f58514-9b73-5dcd-eb34-6debc30ec43a", "yes_price_dollars": "0.5400"}, {"count_fp": "0.91", "created_time": "2026-05-17T09:45:59.428639Z", "no_price_dollars": "0.4600", "taker_book_side": "bid", "taker_outcome_side": "yes", "taker_side": "yes", "ticker": "KXETH15M-26MAY170600-00", "trade_id": "316ed6a0-7b53-769d-61b5-5117931167a6", "yes_price_dollars": "0.5400"}, {"count_fp": "1.00", "created_time": "2026-05-17T09:45:56.224576Z", "no_price_dollars": "0.4500", "taker_book_side": "bid", "taker_outcome_side": "yes", "taker_side": "yes", "ticker": "KXETH15M-26MAY170600-00", "trade_id": "2058cea4-0ab3-505e-13ef-e7be9c3b42df", "yes_price_dollars": "0.5500"}, {"count_fp": "15.24", "created_time": "2026-05-17T09:45:56.120746Z", "no_price_dollars": "0.4500", "taker_book_side": "bid", "taker_outcome_side": "yes", "taker_side": "yes", "ticker": "KXETH15M-26MAY170600-00", "trade_id": "369c3965-c427-4762-f7a0-16597fd15d63", "yes_price_dollars": "0.5500"}, {"count_fp": "3.00", "created_time": "2026-05-17T09:45:50.750533Z", "no_price_dollars": "0.4500", "taker_book_side": "ask", "taker_outcome_side": "no", "taker_side": "no", "ticker": "KXETH15M-26MAY170600-00", "trade_id": "f14be06e-636a-48cf-4d77-7fe824979732", "yes_price_dollars": "0.5500"}, {"count_fp": "1.00", "created_time": "2026-05-17T09:45:50.750533Z", "no_price_dollars": "0.4500", "taker_book_side": "ask", "taker_outcome_side": "no", "taker_side": "no", "ticker": "KXETH15M-26MAY170600-00", "trade_id": "803b599d-c593-4d3b-7428-42e7fb5c73c5", "yes_price_dollars": "0.5500"}, {"count_fp": "21.08", "created_time": "2026-05-17T09:45:50.591226Z", "no_price_dollars": "0.3700", "taker_book_side": "ask", "taker_outcome_side": "no", "taker_side": "no", "ticker": "KXETH15M-26MAY170600-00", "trade_id": "e34891c8-114c-5758-9724-af6262c91bf7", "yes_price_dollars": "0.6300"}, {"count_fp": "19.00", "created_time": "2026-05-17T09:45:49.259981Z", "no_price_dollars": "0.3600", "taker_book_side": "bid", "taker_outcome_side": "yes", "taker_side": "yes", "ticker": "KXETH15M-26MAY170600-00", "trade_id": "d2b0a7df-cb4c-610c-a059-a136a4c0c216", "yes_price_dollars": "0.6400"}, {"count_fp": "75.00", "created_time": "2026-05-17T09:45:47.008395Z", "no_price_dollars": "0.3800", "taker_book_side": "bid", "taker_outcome_side": "yes", "taker_side": "yes", "ticker": "KXETH15M-26MAY170600-00", "trade_id": "fa998440-df99-4565-5cfa-3472be4cf98f", "yes_price_dollars": "0.6200"}, {"count_fp": "1.00", "created_time": "2026-05-17T09:45:46.962919Z", "no_price_dollars": "0.4000", "taker_book_side": "bid", "taker_outcome_side": "yes", "taker_side": "yes", "ticker": "KXETH15M-26MAY170600-00", "trade_id": "1dc095ff-7c9f-5b77-c1b1-56a20075e19a", "yes_price_dollars": "0.6000"}, {"count_fp": "2.00", "created_time": "2026-05-17T09:45:41.750568Z", "no_price_dollars": "0.4100", "taker_book_side": "bid", "taker_outcome_side": "yes", "taker_side": "yes", "ticker": "KXETH15M-26MAY170600-00", "trade_id": "51816c6b-d195-7f5b-023f-1fe8085ca8bf", "yes_price_dollars": "0.5900"}, {"count_fp": "2.50", "created_time": "2026-05-17T09:45:40.346508Z", "no_price_dollars": "0.4100", "taker_book_side": "bid", "taker_outcome_side": "yes", "taker_side": "yes", "ticker": "KXETH15M-26MAY170600-00", "trade_id": "c7e86d92-259d-7acf-b1dc-55b50e114367", "yes_price_dollars": "0.5900"}, {"count_fp": "20.00", "created_time": "2026-05-17T09:45:35.088111Z", "no_price_dollars": "0.4100", "taker_book_side": "bid", "taker_outcome_side": "yes", "taker_side": "yes", "ticker": "KXETH15M-26MAY170600-00", "trade_id": "95765303-12ed-6702-e3b9-4c3c9302b8d4", "yes_price_dollars": "0.5900"}, {"count_fp": "1.00", "created_time": "2026-05-17T09:45:33.761584Z", "no_price_dollars": "0.4200", "taker_book_side": "bid", "taker_outcome_side": "yes", "taker_side": "yes", "ticker": "KXETH15M-26MAY170600-00", "trade_id": "a3baaf5d-eba5-4830-a1bf-510f38b1391f", "yes_price_dollars": "0.5800"}, {"count_fp": "15.00", "created_time": "2026-05-17T09:45:33.761584Z", "no_price_dollars": "0.4200", "taker_book_side": "bid", "taker_outcome_side": "yes", "taker_side": "yes", "ticker": "KXETH15M-26MAY170600-00", "trade_id": "a2bf6c67-a989-4ffe-b234-1ab96dd26425", "yes_price_dollars": "0.5800"}, {"count_fp": "75.00", "created_time": "2026-05-17T09:45:33.757777Z", "no_price_dollars": "0.4400", "taker_book_side": "bid", "taker_outcome_side": "yes", "taker_side": "yes", "ticker": "KXETH15M-26MAY170600-00", "trade_id": "edad4846-d58b-55c0-5525-40650b6b0d94", "yes_price_dollars": "0.5600"}, {"count_fp": "100.00", "created_time": "2026-05-17T09:45:33.745151Z", "no_price_dollars": "0.4800", "taker_book_side": "bid", "taker_outcome_side": "yes", "taker_side": "yes", "ticker": "KXETH15M-26MAY170600-00", "trade_id": "14716dff-2e01-7d09-3d53-abc6ab701d71", "yes_price_dollars": "0.5200"}, {"count_fp": "1.00", "created_time": "2026-05-17T09:45:32.576513Z", "no_price_dollars": "0.4800", "taker_book_side": "bid", "taker_outcome_side": "yes", "taker_side": "yes", "ticker": "KXETH15M-26MAY170600-00", "trade_id": "b18524f7-5416-6fc5-14b9-be9e36d0ed4e", "yes_price_dollars": "0.5200"}, {"count_fp": "2.00", "created_time": "2026-05-17T09:45:24.810668Z", "no_price_dollars": "0.4800", "taker_book_side": "bid", "taker_outcome_side": "yes", "taker_side": "yes", "ticker": "KXETH15M-26MAY170600-00", "trade_id": "72ca07ab-e9fa-5195-5d68-cf90805e1b36", "yes_price_dollars": "0.5200"}, {"count_fp": "3.00", "created_time": "2026-05-17T09:45:23.685222Z", "no_price_dollars": "0.4900", "taker_book_side": "ask", "taker_outcome_side": "no", "taker_side": "no", "ticker": "KXETH15M-26MAY170600-00", "trade_id": "306c4656-9290-5c78-738a-a7e2bdaa20a3", "yes_price_dollars": "0.5100"}, {"count_fp": "2.00", "created_time": "2026-05-17T09:45:18.774648Z", "no_price_dollars": "0.4900", "taker_book_side": "ask", "taker_outcome_side": "no", "taker_side": "no", "ticker": "KXETH15M-26MAY170600-00", "trade_id": "1b1bd04c-3154-6d78-4c1d-c9c5ef04ea4f", "yes_price_dollars": "0.5100"}, {"count_fp": "28.31", "created_time": "2026-05-17T09:45:13.760174Z", "no_price_dollars": "0.5000", "taker_book_side": "ask", "taker_outcome_side": "no", "taker_side": "no", "ticker": "KXETH15M-26MAY170600-00", "trade_id": "d66c0637-1aa0-7e50-90de-45a7b4082d47", "yes_price_dollars": "0.5000"}, {"count_fp": "19.80", "created_time": "2026-05-17T09:45:12.803486Z", "no_price_dollars": "0.4800", "taker_book_side": "bid", "taker_outcome_side": "yes", "taker_side": "yes", "ticker": "KXETH15M-26MAY170600-00", "trade_id": "ed146eb2-a4d0-5e6d-6665-13f7753fcfa3", "yes_price_dollars": "0.5200"}, {"count_fp": "16.20", "created_time": "2026-05-17T09:45:12.803486Z", "no_price_dollars": "0.4700", "taker_book_side": "bid", "taker_outcome_side": "yes", "taker_side": "yes", "ticker": "KXETH15M-26MAY170600-00", "trade_id": "7e230ec0-863e-5487-44c9-d3f4205f12b5", "yes_price_dollars": "0.5300"}, {"count_fp": "12.00", "created_time": "2026-05-17T09:45:11.318961Z", "no_price_dollars": "0.5100", "taker_book_side": "ask", "taker_outcome_side": "no", "taker_side": "no", "ticker": "KXETH15M-26MAY170600-00", "trade_id": "745660d2-4626-731f-9d00-e040ce5aefda", "yes_price_dollars": "0.4900"}, {"count_fp": "0.20", "created_time": "2026-05-17T09:45:07.893432Z", "no_price_dollars": "0.4800", "taker_book_side": "bid", "taker_outcome_side": "yes", "taker_side": "yes", "ticker": "KXETH15M-26MAY170600-00", "trade_id": "4acdfc71-56c0-64f9-af54-65d8f2b6663b", "yes_price_dollars": "0.5200"}]